<root>
  <letter letter_id="SB_J_604">
    <word word_id="SB_J_604.0.0">604.</word>
    <word word_id="SB_J_604.0.1">ANTHONY</word>
    <word word_id="SB_J_604.0.2">CAVE</word>
    <word word_id="SB_J_604.0.3">TO</word>
    <word word_id="SB_J_604.0.4">JOHN</word>
    <word word_id="SB_J_604.0.5">JOHNSON</word>
    <word word_id="SB_J_604.1.0"/>
    <word word_id="SB_J_604.2.0" VARD_fscore_0.1_threshold_0="Annoy" VARD_fscore_0.5_threshold_0="Annoy" VARD_fscore_1.0_threshold_0="Annoy" VARD_fscore_2.0_threshold_0="Annoy">Anno</word>
    <word word_id="SB_J_604.2.1">1548</word>
    <word word_id="SB_J_604.2.2" VARD_fscore_0.1_threshold_0="Jesus," VARD_fscore_0.5_threshold_0="Jesus," VARD_fscore_0.5_threshold_25="Jesus," VARD_fscore_1.0_threshold_0="Jesus," VARD_fscore_2.0_threshold_0="Jesus,">Jhesus,</word>
    <word word_id="SB_J_604.2.3">at</word>
    <word word_id="SB_J_604.2.4">Tickfford,</word>
    <word word_id="SB_J_604.2.5">this</word>
    <word word_id="SB_J_604.2.6" VARD_fscore_0.1_threshold_0="first" VARD_fscore_0.1_threshold_25="first" VARD_fscore_0.1_threshold_50="first" VARD_fscore_0.5_threshold_0="first" VARD_fscore_0.5_threshold_25="first" VARD_fscore_0.5_threshold_50="first" VARD_fscore_0.5_threshold_75="first" VARD_fscore_1.0_threshold_0="first" VARD_fscore_1.0_threshold_25="first" VARD_fscore_1.0_threshold_50="first" VARD_fscore_2.0_threshold_0="first" VARD_fscore_2.0_threshold_25="first" VARD_fscore_2.0_threshold_50="first" VARD_fscore_2.0_threshold_75="first">fyrst</word>
    <word word_id="SB_J_604.2.7">in</word>
    <word word_id="SB_J_604.2.8">December.</word>
    <word word_id="SB_J_604.3.0"/>
    <word word_id="SB_J_604.4.0" VARD_fscore_0.1_threshold_0="After" VARD_fscore_0.5_threshold_0="After" VARD_fscore_0.5_threshold_25="After" VARD_fscore_1.0_threshold_0="After" VARD_fscore_2.0_threshold_0="After">Affter</word>
    <word word_id="SB_J_604.4.1">my</word>
    <word word_id="SB_J_604.4.2" VARD_fscore_0.1_threshold_0="heartiest" VARD_fscore_0.1_threshold_25="heartiest" VARD_fscore_0.1_threshold_50="heartiest" VARD_fscore_0.5_threshold_0="heartiest" VARD_fscore_0.5_threshold_25="heartiest" VARD_fscore_0.5_threshold_50="heartiest" VARD_fscore_1.0_threshold_0="heartiest" VARD_fscore_1.0_threshold_25="heartiest" VARD_fscore_1.0_threshold_50="heartiest" VARD_fscore_2.0_threshold_0="heartiest" VARD_fscore_2.0_threshold_25="heartiest" VARD_fscore_2.0_threshold_50="heartiest">hertyest</word>
    <word word_id="SB_J_604.4.3" VARD_fscore_0.1_threshold_0="recommendation" VARD_fscore_0.5_threshold_0="recommends" VARD_fscore_0.5_threshold_25="recommends" VARD_fscore_1.0_threshold_0="recommendation" VARD_fscore_2.0_threshold_0="recommendation" VARD_fscore_2.0_threshold_25="recommendation">recomendacions</word>
    <word word_id="SB_J_604.4.4">unto</word>
    <word word_id="SB_J_604.4.5" VARD_fscore_0.1_threshold_0="you" VARD_fscore_0.1_threshold_25="you" VARD_fscore_0.1_threshold_50="you" VARD_fscore_0.5_threshold_0="you" VARD_fscore_0.5_threshold_25="you" VARD_fscore_0.5_threshold_50="you" VARD_fscore_0.5_threshold_75="you" VARD_fscore_1.0_threshold_0="you" VARD_fscore_1.0_threshold_25="you" VARD_fscore_1.0_threshold_50="you" VARD_fscore_2.0_threshold_0="you" VARD_fscore_2.0_threshold_25="you" VARD_fscore_2.0_threshold_50="you" VARD_fscore_2.0_threshold_75="you">youe</word>
    <word word_id="SB_J_604.4.6">and</word>
    <word word_id="SB_J_604.4.7">my</word>
    <word word_id="SB_J_604.4.8" VARD_fscore_0.1_threshold_0="cosine" VARD_fscore_0.1_threshold_25="cosine" VARD_fscore_0.5_threshold_0="cosine" VARD_fscore_0.5_threshold_25="cosine" VARD_fscore_0.5_threshold_50="cosine" VARD_fscore_1.0_threshold_0="cosine" VARD_fscore_1.0_threshold_25="cosine" VARD_fscore_2.0_threshold_0="cosine" VARD_fscore_2.0_threshold_25="cosine" VARD_fscore_2.0_threshold_50="cosine">cosyn</word>
    <word word_id="SB_J_604.4.9" VARD_fscore_0.1_threshold_0="booth" VARD_fscore_0.1_threshold_25="booth" VARD_fscore_0.1_threshold_50="booth" VARD_fscore_0.5_threshold_0="booth" VARD_fscore_0.5_threshold_25="booth" VARD_fscore_0.5_threshold_50="booth" VARD_fscore_1.0_threshold_0="booth" VARD_fscore_1.0_threshold_25="booth" VARD_fscore_1.0_threshold_50="booth" VARD_fscore_2.0_threshold_0="booth" VARD_fscore_2.0_threshold_25="booth" VARD_fscore_2.0_threshold_50="booth">boothe</word>
    <word word_id="SB_J_604.4.10">from</word>
    <word word_id="SB_J_604.4.11">me</word>
    <word word_id="SB_J_604.4.12">and</word>
    <word word_id="SB_J_604.4.13">my</word>
    <word word_id="SB_J_604.4.14" VARD_fscore_0.1_threshold_0="wife," VARD_fscore_0.1_threshold_25="wife," VARD_fscore_0.1_threshold_50="wife," VARD_fscore_0.5_threshold_0="wife," VARD_fscore_0.5_threshold_25="wife," VARD_fscore_0.5_threshold_50="wife," VARD_fscore_1.0_threshold_0="wife," VARD_fscore_1.0_threshold_25="wife," VARD_fscore_1.0_threshold_50="wife," VARD_fscore_2.0_threshold_0="wife," VARD_fscore_2.0_threshold_25="wife," VARD_fscore_2.0_threshold_50="wife,">wyff,</word>
    <word word_id="SB_J_604.4.15">being</word>
    <word word_id="SB_J_604.4.16">very</word>
    <word word_id="SB_J_604.4.17" VARD_fscore_0.1_threshold_0="desirous" VARD_fscore_0.5_threshold_0="desirous" VARD_fscore_1.0_threshold_0="desirous" VARD_fscore_2.0_threshold_0="desirous">desyerous</word>
    <word word_id="SB_J_604.4.18">to</word>
    <word word_id="SB_J_604.4.19">here</word>
    <word word_id="SB_J_604.4.20">of</word>
    <word word_id="SB_J_604.4.21">the</word>
    <word word_id="SB_J_604.4.22">good</word>
    <word word_id="SB_J_604.4.23">speed</word>
    <word word_id="SB_J_604.4.24">off</word>
    <word word_id="SB_J_604.4.25">my</word>
    <word word_id="SB_J_604.4.26" VARD_fscore_0.1_threshold_0="cosine" VARD_fscore_0.1_threshold_25="cosine" VARD_fscore_0.5_threshold_0="cosine" VARD_fscore_0.5_threshold_25="cosine" VARD_fscore_0.5_threshold_50="cosine" VARD_fscore_1.0_threshold_0="cosine" VARD_fscore_1.0_threshold_25="cosine" VARD_fscore_2.0_threshold_0="cosine" VARD_fscore_2.0_threshold_25="cosine" VARD_fscore_2.0_threshold_50="cosine">cosyn</word>
    <word word_id="SB_J_604.4.27">your</word>
    <word word_id="SB_J_604.4.28" VARD_fscore_0.1_threshold_0="bedfellow," VARD_fscore_0.5_threshold_0="bedfellow," VARD_fscore_0.5_threshold_25="bedfellow," VARD_fscore_1.0_threshold_0="bedfellow," VARD_fscore_2.0_threshold_0="bedfellow," VARD_fscore_2.0_threshold_25="bedfellow,">bedffellow,</word>
    <word word_id="SB_J_604.4.29">that</word>
    <word word_id="SB_J_604.4.30">God</word>
    <word word_id="SB_J_604.4.31">had</word>
    <word word_id="SB_J_604.4.32">sent</word>
    <word word_id="SB_J_604.4.33" VARD_fscore_0.1_threshold_0="you" VARD_fscore_0.1_threshold_25="you" VARD_fscore_0.1_threshold_50="you" VARD_fscore_0.5_threshold_0="you" VARD_fscore_0.5_threshold_25="you" VARD_fscore_0.5_threshold_50="you" VARD_fscore_0.5_threshold_75="you" VARD_fscore_1.0_threshold_0="you" VARD_fscore_1.0_threshold_25="you" VARD_fscore_1.0_threshold_50="you" VARD_fscore_2.0_threshold_0="you" VARD_fscore_2.0_threshold_25="you" VARD_fscore_2.0_threshold_50="you" VARD_fscore_2.0_threshold_75="you">youe</word>
    <word word_id="SB_J_604.4.34">a</word>
    <word word_id="SB_J_604.4.35">goodly</word>
    <word word_id="SB_J_604.4.36" VARD_fscore_0.1_threshold_0="boy," VARD_fscore_0.1_threshold_25="boy," VARD_fscore_0.1_threshold_50="boy," VARD_fscore_0.5_threshold_0="boy," VARD_fscore_0.5_threshold_25="boy," VARD_fscore_0.5_threshold_50="boy," VARD_fscore_0.5_threshold_75="boy," VARD_fscore_1.0_threshold_0="boy," VARD_fscore_1.0_threshold_25="boy," VARD_fscore_1.0_threshold_50="boy," VARD_fscore_2.0_threshold_0="boy," VARD_fscore_2.0_threshold_25="boy," VARD_fscore_2.0_threshold_50="boy," VARD_fscore_2.0_threshold_75="boy,">boye,</word>
    <word word_id="SB_J_604.4.37">Mr.</word>
    <word word_id="SB_J_604.4.38" VARD_fscore_0.1_threshold_0="Ashley" VARD_fscore_0.5_threshold_0="Ashley" VARD_fscore_1.0_threshold_0="Ashley" VARD_fscore_2.0_threshold_0="Ashley">Asheley</word>
    <word word_id="SB_J_604.4.39" VARD_fscore_0.1_threshold_0="has" VARD_fscore_0.1_threshold_25="has" VARD_fscore_0.1_threshold_50="has" VARD_fscore_0.5_threshold_0="has" VARD_fscore_0.5_threshold_25="has" VARD_fscore_0.5_threshold_50="has" VARD_fscore_1.0_threshold_0="has" VARD_fscore_1.0_threshold_25="has" VARD_fscore_1.0_threshold_50="has" VARD_fscore_2.0_threshold_0="has" VARD_fscore_2.0_threshold_25="has" VARD_fscore_2.0_threshold_50="has">hathe</word>
    <word word_id="SB_J_604.4.40" VARD_fscore_0.1_threshold_0="most" VARD_fscore_0.1_threshold_25="most" VARD_fscore_0.1_threshold_50="most" VARD_fscore_0.5_threshold_0="most" VARD_fscore_0.5_threshold_25="most" VARD_fscore_0.5_threshold_50="most" VARD_fscore_0.5_threshold_75="most" VARD_fscore_1.0_threshold_0="most" VARD_fscore_1.0_threshold_25="most" VARD_fscore_1.0_threshold_50="most" VARD_fscore_2.0_threshold_0="most" VARD_fscore_2.0_threshold_25="most" VARD_fscore_2.0_threshold_50="most" VARD_fscore_2.0_threshold_75="most">moost</word>
    <word word_id="SB_J_604.4.41" VARD_fscore_0.1_threshold_0="heartily" VARD_fscore_0.1_threshold_25="heartily" VARD_fscore_0.1_threshold_50="heartily" VARD_fscore_0.5_threshold_0="heartily" VARD_fscore_0.5_threshold_25="heartily" VARD_fscore_0.5_threshold_50="heartily" VARD_fscore_0.5_threshold_75="heartily" VARD_fscore_1.0_threshold_0="heartily" VARD_fscore_1.0_threshold_25="heartily" VARD_fscore_1.0_threshold_50="heartily" VARD_fscore_2.0_threshold_0="heartily" VARD_fscore_2.0_threshold_25="heartily" VARD_fscore_2.0_threshold_50="heartily" VARD_fscore_2.0_threshold_75="heartily">hertely</word>
    <word word_id="SB_J_604.4.42" VARD_fscore_0.1_threshold_0="thanked" VARD_fscore_0.5_threshold_0="thanked" VARD_fscore_0.5_threshold_25="thanked" VARD_fscore_1.0_threshold_0="thanked" VARD_fscore_2.0_threshold_0="thanked">thancked</word>
    <word word_id="SB_J_604.4.43" VARD_fscore_0.1_threshold_0="you" VARD_fscore_0.1_threshold_25="you" VARD_fscore_0.1_threshold_50="you" VARD_fscore_0.5_threshold_0="you" VARD_fscore_0.5_threshold_25="you" VARD_fscore_0.5_threshold_50="you" VARD_fscore_0.5_threshold_75="you" VARD_fscore_1.0_threshold_0="you" VARD_fscore_1.0_threshold_25="you" VARD_fscore_1.0_threshold_50="you" VARD_fscore_2.0_threshold_0="you" VARD_fscore_2.0_threshold_25="you" VARD_fscore_2.0_threshold_50="you" VARD_fscore_2.0_threshold_75="you">youe</word>
    <word word_id="SB_J_604.4.44">for</word>
    <word word_id="SB_J_604.4.45">your</word>
    <word word_id="SB_J_604.4.46" VARD_fscore_0.1_threshold_0="pains" VARD_fscore_0.1_threshold_25="pains" VARD_fscore_0.1_threshold_50="pains" VARD_fscore_0.5_threshold_0="pains" VARD_fscore_0.5_threshold_25="pains" VARD_fscore_0.5_threshold_50="pains" VARD_fscore_1.0_threshold_0="pains" VARD_fscore_1.0_threshold_25="pains" VARD_fscore_1.0_threshold_50="pains" VARD_fscore_2.0_threshold_0="pains" VARD_fscore_2.0_threshold_25="pains" VARD_fscore_2.0_threshold_50="pains">peynes</word>
    <word word_id="SB_J_604.4.47">ye</word>
    <word word_id="SB_J_604.4.48">toke</word>
    <word word_id="SB_J_604.4.49">here;</word>
    <word word_id="SB_J_604.4.50">and</word>
    <word word_id="SB_J_604.4.51" VARD_fscore_0.1_threshold_0="now" VARD_fscore_0.1_threshold_25="now" VARD_fscore_0.1_threshold_50="now" VARD_fscore_0.5_threshold_0="now" VARD_fscore_0.5_threshold_25="now" VARD_fscore_0.5_threshold_50="now" VARD_fscore_0.5_threshold_75="now" VARD_fscore_1.0_threshold_0="now" VARD_fscore_1.0_threshold_25="now" VARD_fscore_1.0_threshold_50="now" VARD_fscore_2.0_threshold_0="now" VARD_fscore_2.0_threshold_25="now" VARD_fscore_2.0_threshold_50="now" VARD_fscore_2.0_threshold_75="now">nowe</word>
    <word word_id="SB_J_604.4.52">send</word>
    <word word_id="SB_J_604.4.53">this</word>
    <word word_id="SB_J_604.4.54" VARD_fscore_0.1_threshold_0="bearer" VARD_fscore_0.1_threshold_25="bearer" VARD_fscore_0.5_threshold_0="bearer" VARD_fscore_0.5_threshold_25="bearer" VARD_fscore_0.5_threshold_50="bearer" VARD_fscore_1.0_threshold_0="bearer" VARD_fscore_1.0_threshold_25="bearer" VARD_fscore_2.0_threshold_0="bearer" VARD_fscore_2.0_threshold_25="bearer">berer</word>
    <word word_id="SB_J_604.4.55">unto</word>
    <word word_id="SB_J_604.4.56" VARD_fscore_0.1_threshold_0="you" VARD_fscore_0.1_threshold_25="you" VARD_fscore_0.1_threshold_50="you" VARD_fscore_0.5_threshold_0="you" VARD_fscore_0.5_threshold_25="you" VARD_fscore_0.5_threshold_50="you" VARD_fscore_0.5_threshold_75="you" VARD_fscore_1.0_threshold_0="you" VARD_fscore_1.0_threshold_25="you" VARD_fscore_1.0_threshold_50="you" VARD_fscore_2.0_threshold_0="you" VARD_fscore_2.0_threshold_25="you" VARD_fscore_2.0_threshold_50="you" VARD_fscore_2.0_threshold_75="you">youe</word>
    <word word_id="SB_J_604.4.57">to</word>
    <word word_id="SB_J_604.4.58" VARD_fscore_0.1_threshold_0="know" VARD_fscore_0.1_threshold_25="know" VARD_fscore_0.1_threshold_50="know" VARD_fscore_0.5_threshold_0="know" VARD_fscore_0.5_threshold_25="know" VARD_fscore_0.5_threshold_50="know" VARD_fscore_0.5_threshold_75="know" VARD_fscore_1.0_threshold_0="know" VARD_fscore_1.0_threshold_25="know" VARD_fscore_1.0_threshold_50="know" VARD_fscore_2.0_threshold_0="know" VARD_fscore_2.0_threshold_25="know" VARD_fscore_2.0_threshold_50="know" VARD_fscore_2.0_threshold_75="know">knowe</word>
    <word word_id="SB_J_604.4.59">howe</word>
    <word word_id="SB_J_604.4.60">ye</word>
    <word word_id="SB_J_604.4.61">all</word>
    <word word_id="SB_J_604.4.62" VARD_fscore_0.1_threshold_0="too," VARD_fscore_0.1_threshold_25="too," VARD_fscore_0.5_threshold_0="do," VARD_fscore_0.5_threshold_25="do," VARD_fscore_0.5_threshold_50="do," VARD_fscore_1.0_threshold_0="too," VARD_fscore_1.0_threshold_25="too," VARD_fscore_2.0_threshold_0="do," VARD_fscore_2.0_threshold_25="do,">doo,</word>
    <word word_id="SB_J_604.4.63">and</word>
    <word word_id="SB_J_604.4.64">to</word>
    <word word_id="SB_J_604.4.65" VARD_fscore_0.1_threshold_0="bring" VARD_fscore_0.1_threshold_25="bring" VARD_fscore_0.1_threshold_50="bring" VARD_fscore_0.5_threshold_0="bring" VARD_fscore_0.5_threshold_25="bring" VARD_fscore_0.5_threshold_50="bring" VARD_fscore_0.5_threshold_75="bring" VARD_fscore_1.0_threshold_0="bring" VARD_fscore_1.0_threshold_25="bring" VARD_fscore_1.0_threshold_50="bring" VARD_fscore_2.0_threshold_0="bring" VARD_fscore_2.0_threshold_25="bring" VARD_fscore_2.0_threshold_50="bring" VARD_fscore_2.0_threshold_75="bring">bryng</word>
    <word word_id="SB_J_604.4.66">xx</word>
    <word word_id="SB_J_604.4.67" VARD_fscore_0.1_threshold_0="dozen" VARD_fscore_0.1_threshold_25="dozen" VARD_fscore_0.1_threshold_50="dozen" VARD_fscore_0.5_threshold_0="dozen" VARD_fscore_0.5_threshold_25="dozen" VARD_fscore_0.5_threshold_50="dozen" VARD_fscore_1.0_threshold_0="dozen" VARD_fscore_1.0_threshold_25="dozen" VARD_fscore_1.0_threshold_50="dozen" VARD_fscore_2.0_threshold_0="dozen" VARD_fscore_2.0_threshold_25="dozen" VARD_fscore_2.0_threshold_50="dozen">dossen</word>
    <word word_id="SB_J_604.4.68" VARD_fscore_0.1_threshold_0="candle" VARD_fscore_0.1_threshold_25="candle" VARD_fscore_0.1_threshold_50="candle" VARD_fscore_0.5_threshold_0="candle" VARD_fscore_0.5_threshold_25="candle" VARD_fscore_0.5_threshold_50="candle" VARD_fscore_1.0_threshold_0="candle" VARD_fscore_1.0_threshold_25="candle" VARD_fscore_1.0_threshold_50="candle" VARD_fscore_2.0_threshold_0="candle" VARD_fscore_2.0_threshold_25="candle" VARD_fscore_2.0_threshold_50="candle">candell</word>
    <word word_id="SB_J_604.4.69">for</word>
    <word word_id="SB_J_604.4.70">Morton,</word>
    <word word_id="SB_J_604.4.71">but</word>
    <word word_id="SB_J_604.4.72">ye</word>
    <word word_id="SB_J_604.4.73">must</word>
    <word word_id="SB_J_604.4.74">be</word>
    <word word_id="SB_J_604.4.75">my</word>
    <word word_id="SB_J_604.4.76" VARD_fscore_0.1_threshold_0="seaworthy," VARD_fscore_0.5_threshold_0="seaworthy," VARD_fscore_1.0_threshold_0="seaworthy," VARD_fscore_2.0_threshold_0="seaworthy,">sewrty,</word>
    <word word_id="SB_J_604.4.77">for</word>
    <word word_id="SB_J_604.4.78">I</word>
    <word word_id="SB_J_604.4.79">send</word>
    <word word_id="SB_J_604.4.80" VARD_fscore_0.1_threshold_0="no" VARD_fscore_0.1_threshold_25="no" VARD_fscore_0.1_threshold_50="no" VARD_fscore_0.5_threshold_0="no" VARD_fscore_0.5_threshold_25="no" VARD_fscore_0.5_threshold_50="no" VARD_fscore_1.0_threshold_0="no" VARD_fscore_1.0_threshold_25="no" VARD_fscore_1.0_threshold_50="no" VARD_fscore_2.0_threshold_0="no" VARD_fscore_2.0_threshold_25="no" VARD_fscore_2.0_threshold_50="no">noo</word>
    <word word_id="SB_J_604.4.81" VARD_fscore_0.1_threshold_0="money." VARD_fscore_0.1_threshold_25="money." VARD_fscore_0.1_threshold_50="money." VARD_fscore_0.5_threshold_0="money." VARD_fscore_0.5_threshold_25="money." VARD_fscore_0.5_threshold_50="money." VARD_fscore_1.0_threshold_0="money." VARD_fscore_1.0_threshold_25="money." VARD_fscore_1.0_threshold_50="money." VARD_fscore_2.0_threshold_0="money." VARD_fscore_2.0_threshold_25="money." VARD_fscore_2.0_threshold_50="money.">monneye.</word>
    <word word_id="SB_J_604.5.0" VARD_fscore_0.1_threshold_0="Sins" VARD_fscore_0.1_threshold_25="Sins" VARD_fscore_0.5_threshold_0="Sins" VARD_fscore_0.5_threshold_25="Sins" VARD_fscore_0.5_threshold_50="Sins" VARD_fscore_1.0_threshold_0="Sins" VARD_fscore_1.0_threshold_25="Sins" VARD_fscore_2.0_threshold_0="Sins" VARD_fscore_2.0_threshold_25="Sins">Syns</word>
    <word word_id="SB_J_604.5.1">your</word>
    <word word_id="SB_J_604.5.2">being</word>
    <word word_id="SB_J_604.5.3">here,</word>
    <word word_id="SB_J_604.5.4">I</word>
    <word word_id="SB_J_604.5.5" VARD_fscore_0.1_threshold_0="find" VARD_fscore_0.1_threshold_25="find" VARD_fscore_0.1_threshold_50="find" VARD_fscore_0.5_threshold_0="find" VARD_fscore_0.5_threshold_25="find" VARD_fscore_0.5_threshold_50="find" VARD_fscore_0.5_threshold_75="find" VARD_fscore_1.0_threshold_0="find" VARD_fscore_1.0_threshold_25="find" VARD_fscore_1.0_threshold_50="find" VARD_fscore_2.0_threshold_0="find" VARD_fscore_2.0_threshold_25="find" VARD_fscore_2.0_threshold_50="find" VARD_fscore_2.0_threshold_75="find">fynd</word>
    <word word_id="SB_J_604.5.6">that</word>
    <word word_id="SB_J_604.5.7">ye</word>
    <word word_id="SB_J_604.5.8">had</word>
    <word word_id="SB_J_604.5.9">xli</word>
    <word word_id="SB_J_604.5.10">of</word>
    <word word_id="SB_J_604.5.11">me</word>
    <word word_id="SB_J_604.5.12">here</word>
    <word word_id="SB_J_604.5.13">on</word>
    <word word_id="SB_J_604.5.14" VARD_fscore_0.1_threshold_0="our" VARD_fscore_0.1_threshold_25="our" VARD_fscore_0.1_threshold_50="our" VARD_fscore_0.5_threshold_0="our" VARD_fscore_0.5_threshold_25="our" VARD_fscore_0.5_threshold_50="our" VARD_fscore_1.0_threshold_0="our" VARD_fscore_1.0_threshold_25="our" VARD_fscore_1.0_threshold_50="our" VARD_fscore_2.0_threshold_0="our" VARD_fscore_2.0_threshold_25="our" VARD_fscore_2.0_threshold_50="our">owre</word>
    <word word_id="SB_J_604.5.15" VARD_fscore_0.1_threshold_0="exempt" VARD_fscore_0.1_threshold_25="exempt" VARD_fscore_0.5_threshold_0="exempt" VARD_fscore_0.5_threshold_25="exempt" VARD_fscore_1.0_threshold_0="exempt" VARD_fscore_1.0_threshold_25="exempt" VARD_fscore_2.0_threshold_0="exempt" VARD_fscore_2.0_threshold_25="exempt">acompt</word>
    <word word_id="SB_J_604.5.16">of</word>
    <word word_id="SB_J_604.5.17" VARD_fscore_0.1_threshold_0="fellas," VARD_fscore_0.5_threshold_0="fellas," VARD_fscore_0.5_threshold_25="fellas," VARD_fscore_0.5_threshold_50="fellas," VARD_fscore_1.0_threshold_0="fellas," VARD_fscore_2.0_threshold_0="fellas," VARD_fscore_2.0_threshold_25="fellas,">felles,</word>
    <word word_id="SB_J_604.5.18">moore</word>
    <word word_id="SB_J_604.5.19">then</word>
    <word word_id="SB_J_604.5.20" VARD_fscore_0.1_threshold_0="you" VARD_fscore_0.1_threshold_25="you" VARD_fscore_0.1_threshold_50="you" VARD_fscore_0.5_threshold_0="you" VARD_fscore_0.5_threshold_25="you" VARD_fscore_0.5_threshold_50="you" VARD_fscore_0.5_threshold_75="you" VARD_fscore_1.0_threshold_0="you" VARD_fscore_1.0_threshold_25="you" VARD_fscore_1.0_threshold_50="you" VARD_fscore_2.0_threshold_0="you" VARD_fscore_2.0_threshold_25="you" VARD_fscore_2.0_threshold_50="you" VARD_fscore_2.0_threshold_75="you">youe</word>
    <word word_id="SB_J_604.5.21">put</word>
    <word word_id="SB_J_604.5.22">into</word>
    <word word_id="SB_J_604.5.23">the</word>
    <word word_id="SB_J_604.5.24" VARD_fscore_0.1_threshold_0="reckoning" VARD_fscore_0.5_threshold_0="reckoning" VARD_fscore_0.5_threshold_25="reckoning" VARD_fscore_1.0_threshold_0="reckoning" VARD_fscore_2.0_threshold_0="reckoning">reconnyng</word>
    <word word_id="SB_J_604.5.25">paid</word>
    <word word_id="SB_J_604.5.26">in</word>
    <word word_id="SB_J_604.5.27" VARD_fscore_0.1_threshold_0="July," VARD_fscore_0.1_threshold_25="July," VARD_fscore_0.5_threshold_0="July," VARD_fscore_0.5_threshold_25="July," VARD_fscore_0.5_threshold_50="July," VARD_fscore_1.0_threshold_0="July," VARD_fscore_1.0_threshold_25="July," VARD_fscore_2.0_threshold_0="July," VARD_fscore_2.0_threshold_25="July," VARD_fscore_2.0_threshold_50="July,">Jully,</word>
    <word word_id="SB_J_604.5.28">and</word>
    <word word_id="SB_J_604.5.29">xli</word>
    <word word_id="SB_J_604.5.30">moore</word>
    <word word_id="SB_J_604.5.31">sent</word>
    <word word_id="SB_J_604.5.32">per</word>
    <word word_id="SB_J_604.5.33">Clement</word>
    <word word_id="SB_J_604.5.34" VARD_fscore_0.1_threshold_0="Smith" VARD_fscore_0.1_threshold_25="Smith" VARD_fscore_0.1_threshold_50="Smith" VARD_fscore_0.5_threshold_0="Smith" VARD_fscore_0.5_threshold_25="Smith" VARD_fscore_0.5_threshold_50="Smith" VARD_fscore_1.0_threshold_0="Smith" VARD_fscore_1.0_threshold_25="Smith" VARD_fscore_1.0_threshold_50="Smith" VARD_fscore_2.0_threshold_0="Smith" VARD_fscore_2.0_threshold_25="Smith" VARD_fscore_2.0_threshold_50="Smith">Smyth</word>
    <word word_id="SB_J_604.5.35">in</word>
    <word word_id="SB_J_604.5.36">August;</word>
    <word word_id="SB_J_604.5.37">what</word>
    <word word_id="SB_J_604.5.38">moore</word>
    <word word_id="SB_J_604.5.39">I</word>
    <word word_id="SB_J_604.5.40">shall</word>
    <word word_id="SB_J_604.5.41" VARD_fscore_0.1_threshold_0="find" VARD_fscore_0.1_threshold_25="find" VARD_fscore_0.1_threshold_50="find" VARD_fscore_0.5_threshold_0="find" VARD_fscore_0.5_threshold_25="find" VARD_fscore_0.5_threshold_50="find" VARD_fscore_0.5_threshold_75="find" VARD_fscore_1.0_threshold_0="find" VARD_fscore_1.0_threshold_25="find" VARD_fscore_1.0_threshold_50="find" VARD_fscore_2.0_threshold_0="find" VARD_fscore_2.0_threshold_25="find" VARD_fscore_2.0_threshold_50="find" VARD_fscore_2.0_threshold_75="find">fynd</word>
    <word word_id="SB_J_604.5.42">I</word>
    <word word_id="SB_J_604.5.43">cannot</word>
    <word word_id="SB_J_604.5.44">yet</word>
    <word word_id="SB_J_604.5.45">tell.</word>
    <word word_id="SB_J_604.5.46">At</word>
    <word word_id="SB_J_604.5.47" VARD_fscore_0.1_threshold_0="our" VARD_fscore_0.1_threshold_25="our" VARD_fscore_0.1_threshold_50="our" VARD_fscore_0.5_threshold_0="our" VARD_fscore_0.5_threshold_25="our" VARD_fscore_0.5_threshold_50="our" VARD_fscore_1.0_threshold_0="our" VARD_fscore_1.0_threshold_25="our" VARD_fscore_1.0_threshold_50="our" VARD_fscore_2.0_threshold_0="our" VARD_fscore_2.0_threshold_25="our" VARD_fscore_2.0_threshold_50="our">owre</word>
    <word word_id="SB_J_604.5.48">next</word>
    <word word_id="SB_J_604.5.49" VARD_fscore_0.1_threshold_0="moating" VARD_fscore_0.1_threshold_25="moating" VARD_fscore_0.5_threshold_0="moating" VARD_fscore_0.5_threshold_25="moating" VARD_fscore_0.5_threshold_50="moating" VARD_fscore_1.0_threshold_0="moating" VARD_fscore_1.0_threshold_25="moating" VARD_fscore_2.0_threshold_0="moating" VARD_fscore_2.0_threshold_25="moating">meatyng</word>
    <word word_id="SB_J_604.5.50">my</word>
    <word word_id="SB_J_604.5.51">trust</word>
    <word word_id="SB_J_604.5.52">is</word>
    <word word_id="SB_J_604.5.53">ye</word>
    <word word_id="SB_J_604.5.54">will</word>
    <word word_id="SB_J_604.5.55" VARD_fscore_0.1_threshold_0="appoint" VARD_fscore_0.1_threshold_25="appoint" VARD_fscore_0.5_threshold_0="appoint" VARD_fscore_0.5_threshold_25="appoint" VARD_fscore_0.5_threshold_50="appoint" VARD_fscore_1.0_threshold_0="appoint" VARD_fscore_1.0_threshold_25="appoint" VARD_fscore_2.0_threshold_0="appoint" VARD_fscore_2.0_threshold_25="appoint" VARD_fscore_2.0_threshold_50="appoint">apoint</word>
    <word word_id="SB_J_604.5.56">that</word>
    <word word_id="SB_J_604.5.57">we</word>
    <word word_id="SB_J_604.5.58" VARD_fscore_0.1_threshold_0="may" VARD_fscore_0.1_threshold_25="may" VARD_fscore_0.1_threshold_50="may" VARD_fscore_0.5_threshold_0="may" VARD_fscore_0.5_threshold_25="may" VARD_fscore_0.5_threshold_50="may" VARD_fscore_0.5_threshold_75="may" VARD_fscore_1.0_threshold_0="may" VARD_fscore_1.0_threshold_25="may" VARD_fscore_1.0_threshold_50="may" VARD_fscore_2.0_threshold_0="may" VARD_fscore_2.0_threshold_25="may" VARD_fscore_2.0_threshold_50="may" VARD_fscore_2.0_threshold_75="may">maye</word>
    <word word_id="SB_J_604.5.59">with</word>
    <word word_id="SB_J_604.5.60" VARD_fscore_0.1_threshold_0="leisure" VARD_fscore_0.1_threshold_25="leisure" VARD_fscore_0.1_threshold_50="leisure" VARD_fscore_0.5_threshold_0="leisure" VARD_fscore_0.5_threshold_25="leisure" VARD_fscore_0.5_threshold_50="leisure" VARD_fscore_1.0_threshold_0="leisure" VARD_fscore_1.0_threshold_25="leisure" VARD_fscore_1.0_threshold_50="leisure" VARD_fscore_2.0_threshold_0="leisure" VARD_fscore_2.0_threshold_25="leisure" VARD_fscore_2.0_threshold_50="leisure">lesure</word>
    <word word_id="SB_J_604.5.61" VARD_fscore_0.1_threshold_0="clear" VARD_fscore_0.1_threshold_25="clear" VARD_fscore_0.1_threshold_50="clear" VARD_fscore_0.5_threshold_0="clear" VARD_fscore_0.5_threshold_25="clear" VARD_fscore_0.5_threshold_50="clear" VARD_fscore_0.5_threshold_75="clear" VARD_fscore_1.0_threshold_0="clear" VARD_fscore_1.0_threshold_25="clear" VARD_fscore_1.0_threshold_50="clear" VARD_fscore_2.0_threshold_0="clear" VARD_fscore_2.0_threshold_25="clear" VARD_fscore_2.0_threshold_50="clear" VARD_fscore_2.0_threshold_75="clear">clere</word>
    <word word_id="SB_J_604.5.62">all</word>
    <word word_id="SB_J_604.5.63">former</word>
    <word word_id="SB_J_604.5.64" VARD_fscore_0.1_threshold_0="recommences," VARD_fscore_0.5_threshold_0="recommences," VARD_fscore_0.5_threshold_25="recommences," VARD_fscore_1.0_threshold_0="recommences," VARD_fscore_2.0_threshold_0="recommences," VARD_fscore_2.0_threshold_25="recommences,">reconnynges,</word>
    <word word_id="SB_J_604.5.65">for</word>
    <word word_id="SB_J_604.5.66" VARD_fscore_0.1_threshold_0="booth" VARD_fscore_0.1_threshold_25="booth" VARD_fscore_0.1_threshold_50="booth" VARD_fscore_0.5_threshold_0="booth" VARD_fscore_0.5_threshold_25="booth" VARD_fscore_0.5_threshold_50="booth" VARD_fscore_1.0_threshold_0="booth" VARD_fscore_1.0_threshold_25="booth" VARD_fscore_1.0_threshold_50="booth" VARD_fscore_2.0_threshold_0="booth" VARD_fscore_2.0_threshold_25="booth" VARD_fscore_2.0_threshold_50="booth">boothe</word>
    <word word_id="SB_J_604.5.67" VARD_fscore_0.1_threshold_0="our" VARD_fscore_0.1_threshold_25="our" VARD_fscore_0.1_threshold_50="our" VARD_fscore_0.5_threshold_0="our" VARD_fscore_0.5_threshold_25="our" VARD_fscore_0.5_threshold_50="our" VARD_fscore_1.0_threshold_0="our" VARD_fscore_1.0_threshold_25="our" VARD_fscore_1.0_threshold_50="our" VARD_fscore_2.0_threshold_0="our" VARD_fscore_2.0_threshold_25="our" VARD_fscore_2.0_threshold_50="our">owre</word>
    <word word_id="SB_J_604.5.68" VARD_fscore_0.1_threshold_0="quietness," VARD_fscore_0.1_threshold_25="quietness," VARD_fscore_0.1_threshold_50="quietness," VARD_fscore_0.5_threshold_0="quietness," VARD_fscore_0.5_threshold_25="quietness," VARD_fscore_0.5_threshold_50="quietness," VARD_fscore_0.5_threshold_75="quietness," VARD_fscore_1.0_threshold_0="quietness," VARD_fscore_1.0_threshold_25="quietness," VARD_fscore_1.0_threshold_50="quietness," VARD_fscore_2.0_threshold_0="quietness," VARD_fscore_2.0_threshold_25="quietness," VARD_fscore_2.0_threshold_50="quietness," VARD_fscore_2.0_threshold_75="quietness,">quietnes,</word>
    <word word_id="SB_J_604.5.69">and</word>
    <word word_id="SB_J_604.5.70">trust</word>
    <word word_id="SB_J_604.5.71">God</word>
    <word word_id="SB_J_604.5.72">shall</word>
    <word word_id="SB_J_604.5.73">make</word>
    <word word_id="SB_J_604.5.74">my</word>
    <word word_id="SB_J_604.5.75" VARD_fscore_0.1_threshold_0="cosine" VARD_fscore_0.1_threshold_25="cosine" VARD_fscore_0.5_threshold_0="cosine" VARD_fscore_0.5_threshold_25="cosine" VARD_fscore_0.5_threshold_50="cosine" VARD_fscore_1.0_threshold_0="cosine" VARD_fscore_1.0_threshold_25="cosine" VARD_fscore_2.0_threshold_0="cosine" VARD_fscore_2.0_threshold_25="cosine" VARD_fscore_2.0_threshold_50="cosine">cosyn</word>
    <word word_id="SB_J_604.5.76">strong</word>
    <word word_id="SB_J_604.5.77">to</word>
    <word word_id="SB_J_604.5.78" VARD_fscore_0.1_threshold_0="come" VARD_fscore_0.1_threshold_25="come" VARD_fscore_0.5_threshold_0="come" VARD_fscore_0.5_threshold_25="come" VARD_fscore_0.5_threshold_50="come" VARD_fscore_1.0_threshold_0="come" VARD_fscore_1.0_threshold_25="come" VARD_fscore_2.0_threshold_0="come" VARD_fscore_2.0_threshold_25="come" VARD_fscore_2.0_threshold_50="come">com</word>
    <word word_id="SB_J_604.5.79">with</word>
    <word word_id="SB_J_604.5.80" VARD_fscore_0.1_threshold_0="you." VARD_fscore_0.1_threshold_25="you." VARD_fscore_0.1_threshold_50="you." VARD_fscore_0.5_threshold_0="you." VARD_fscore_0.5_threshold_25="you." VARD_fscore_0.5_threshold_50="you." VARD_fscore_0.5_threshold_75="you." VARD_fscore_1.0_threshold_0="you." VARD_fscore_1.0_threshold_25="you." VARD_fscore_1.0_threshold_50="you." VARD_fscore_2.0_threshold_0="you." VARD_fscore_2.0_threshold_25="you." VARD_fscore_2.0_threshold_50="you." VARD_fscore_2.0_threshold_75="you.">youe.</word>
    <word word_id="SB_J_604.5.81">I</word>
    <word word_id="SB_J_604.5.82">have</word>
    <word word_id="SB_J_604.5.83" VARD_fscore_0.1_threshold_0="so" VARD_fscore_0.1_threshold_25="so" VARD_fscore_0.1_threshold_50="so" VARD_fscore_0.5_threshold_0="so" VARD_fscore_0.5_threshold_25="so" VARD_fscore_0.5_threshold_50="so" VARD_fscore_1.0_threshold_0="so" VARD_fscore_1.0_threshold_25="so" VARD_fscore_1.0_threshold_50="so" VARD_fscore_2.0_threshold_0="so" VARD_fscore_2.0_threshold_25="so" VARD_fscore_2.0_threshold_50="so">soo</word>
    <word word_id="SB_J_604.5.84">charged</word>
    <word word_id="SB_J_604.5.85" VARD_fscore_0.1_threshold_0="myself" VARD_fscore_0.1_threshold_25="myself" VARD_fscore_0.1_threshold_50="myself" VARD_fscore_0.5_threshold_0="myself" VARD_fscore_0.5_threshold_25="myself" VARD_fscore_0.5_threshold_50="myself" VARD_fscore_1.0_threshold_0="myself" VARD_fscore_1.0_threshold_25="myself" VARD_fscore_1.0_threshold_50="myself" VARD_fscore_2.0_threshold_0="myself" VARD_fscore_2.0_threshold_25="myself" VARD_fscore_2.0_threshold_50="myself">mysellf</word>
    <word word_id="SB_J_604.5.86">with</word>
    <word word_id="SB_J_604.5.87" VARD_fscore_0.1_threshold_0="willies" VARD_fscore_0.5_threshold_0="willies" VARD_fscore_1.0_threshold_0="willies" VARD_fscore_2.0_threshold_0="willies">wulles</word>
    <word word_id="SB_J_604.5.88" VARD_fscore_0.1_threshold_0="tenet" VARD_fscore_0.5_threshold_0="tenet" VARD_fscore_1.0_threshold_0="tenet" VARD_fscore_2.0_threshold_0="tenet">tnat</word>
    <word word_id="SB_J_604.5.89">I</word>
    <word word_id="SB_J_604.5.90">cannot</word>
    <word word_id="SB_J_604.5.91" VARD_fscore_0.1_threshold_0="perceive" VARD_fscore_0.1_threshold_25="perceive" VARD_fscore_0.1_threshold_50="perceive" VARD_fscore_0.5_threshold_0="perceive" VARD_fscore_0.5_threshold_25="perceive" VARD_fscore_0.5_threshold_50="perceive" VARD_fscore_1.0_threshold_0="perceive" VARD_fscore_1.0_threshold_25="perceive" VARD_fscore_1.0_threshold_50="perceive" VARD_fscore_2.0_threshold_0="perceive" VARD_fscore_2.0_threshold_25="perceive" VARD_fscore_2.0_threshold_50="perceive">perceave</word>
    <word word_id="SB_J_604.5.92">howe</word>
    <word word_id="SB_J_604.5.93">I</word>
    <word word_id="SB_J_604.5.94">may</word>
    <word word_id="SB_J_604.5.95" VARD_fscore_0.1_threshold_0="model" VARD_fscore_0.5_threshold_0="model" VARD_fscore_0.5_threshold_25="model" VARD_fscore_0.5_threshold_50="model" VARD_fscore_1.0_threshold_0="model" VARD_fscore_2.0_threshold_0="model" VARD_fscore_2.0_threshold_25="model">medel</word>
    <word word_id="SB_J_604.5.96">with</word>
    <word word_id="SB_J_604.5.97" VARD_fscore_0.1_threshold_0="any" VARD_fscore_0.1_threshold_25="any" VARD_fscore_0.5_threshold_0="any" VARD_fscore_0.5_threshold_25="any" VARD_fscore_0.5_threshold_50="any" VARD_fscore_1.0_threshold_0="any" VARD_fscore_1.0_threshold_25="any" VARD_fscore_2.0_threshold_0="any" VARD_fscore_2.0_threshold_25="any" VARD_fscore_2.0_threshold_50="any">anny</word>
    <word word_id="SB_J_604.5.98" VARD_fscore_0.1_threshold_0="country" VARD_fscore_0.1_threshold_25="country" VARD_fscore_0.1_threshold_50="country" VARD_fscore_0.5_threshold_0="country" VARD_fscore_0.5_threshold_25="country" VARD_fscore_0.5_threshold_50="country" VARD_fscore_0.5_threshold_75="country" VARD_fscore_1.0_threshold_0="country" VARD_fscore_1.0_threshold_25="country" VARD_fscore_1.0_threshold_50="country" VARD_fscore_2.0_threshold_0="country" VARD_fscore_2.0_threshold_25="country" VARD_fscore_2.0_threshold_50="country" VARD_fscore_2.0_threshold_75="country">contrey</word>
    <word word_id="SB_J_604.5.99" VARD_fscore_0.1_threshold_0="fellas" VARD_fscore_0.5_threshold_0="fellas" VARD_fscore_0.5_threshold_25="fellas" VARD_fscore_0.5_threshold_50="fellas" VARD_fscore_1.0_threshold_0="fellas" VARD_fscore_2.0_threshold_0="fellas" VARD_fscore_2.0_threshold_25="fellas">felles</word>
    <word word_id="SB_J_604.5.100">in</word>
    <word word_id="SB_J_604.5.101">your</word>
    <word word_id="SB_J_604.5.102" VARD_fscore_0.1_threshold_0="parties" VARD_fscore_0.1_threshold_25="parties" VARD_fscore_0.1_threshold_50="parties" VARD_fscore_0.5_threshold_0="parties" VARD_fscore_0.5_threshold_25="parties" VARD_fscore_0.5_threshold_50="parties" VARD_fscore_0.5_threshold_75="parties" VARD_fscore_1.0_threshold_0="parties" VARD_fscore_1.0_threshold_25="parties" VARD_fscore_1.0_threshold_50="parties" VARD_fscore_2.0_threshold_0="parties" VARD_fscore_2.0_threshold_25="parties" VARD_fscore_2.0_threshold_50="parties" VARD_fscore_2.0_threshold_75="parties">partyes</word>
    <word word_id="SB_J_604.5.103">this</word>
    <word word_id="SB_J_604.5.104" VARD_fscore_0.1_threshold_0="year," VARD_fscore_0.1_threshold_25="year," VARD_fscore_0.1_threshold_50="year," VARD_fscore_0.5_threshold_0="year," VARD_fscore_0.5_threshold_25="year," VARD_fscore_0.5_threshold_50="year," VARD_fscore_0.5_threshold_75="year," VARD_fscore_1.0_threshold_0="year," VARD_fscore_1.0_threshold_25="year," VARD_fscore_1.0_threshold_50="year," VARD_fscore_2.0_threshold_0="year," VARD_fscore_2.0_threshold_25="year," VARD_fscore_2.0_threshold_50="year," VARD_fscore_2.0_threshold_75="year,">yere,</word>
    <word word_id="SB_J_604.5.105" VARD_fscore_0.1_threshold_0="therefore" VARD_fscore_0.1_threshold_25="therefore" VARD_fscore_0.1_threshold_50="therefore" VARD_fscore_0.5_threshold_0="therefore" VARD_fscore_0.5_threshold_25="therefore" VARD_fscore_0.5_threshold_50="therefore" VARD_fscore_0.5_threshold_75="therefore" VARD_fscore_1.0_threshold_0="therefore" VARD_fscore_1.0_threshold_25="therefore" VARD_fscore_1.0_threshold_50="therefore" VARD_fscore_2.0_threshold_0="therefore" VARD_fscore_2.0_threshold_25="therefore" VARD_fscore_2.0_threshold_50="therefore" VARD_fscore_2.0_threshold_75="therefore">therfore</word>
    <word word_id="SB_J_604.5.106">ye</word>
    <word word_id="SB_J_604.5.107">may</word>
    <word word_id="SB_J_604.5.108">use</word>
    <word word_id="SB_J_604.5.109" VARD_fscore_0.1_threshold_0="thereafter" VARD_fscore_0.5_threshold_0="thereafter" VARD_fscore_0.5_threshold_25="thereafter" VARD_fscore_1.0_threshold_0="thereafter" VARD_fscore_2.0_threshold_0="thereafter" VARD_fscore_2.0_threshold_25="thereafter">thereaffter</word>
    <word word_id="SB_J_604.5.110">with</word>
    <word word_id="SB_J_604.5.111">those</word>
    <word word_id="SB_J_604.5.112">ye</word>
    <word word_id="SB_J_604.5.113">have</word>
    <word word_id="SB_J_604.5.114">to</word>
    <word word_id="SB_J_604.5.115">do</word>
    <word word_id="SB_J_604.5.116">with,</word>
    <word word_id="SB_J_604.5.117">for</word>
    <word word_id="SB_J_604.5.118">I</word>
    <word word_id="SB_J_604.5.119" VARD_fscore_0.1_threshold_0="intend" VARD_fscore_0.1_threshold_25="intend" VARD_fscore_0.5_threshold_0="intend" VARD_fscore_0.5_threshold_25="intend" VARD_fscore_0.5_threshold_50="intend" VARD_fscore_1.0_threshold_0="intend" VARD_fscore_1.0_threshold_25="intend" VARD_fscore_2.0_threshold_0="intend" VARD_fscore_2.0_threshold_25="intend">entend</word>
    <word word_id="SB_J_604.5.120">not</word>
    <word word_id="SB_J_604.5.121">to</word>
    <word word_id="SB_J_604.5.122" VARD_fscore_0.1_threshold_0="mettle" VARD_fscore_0.1_threshold_25="mettle" VARD_fscore_0.1_threshold_50="mettle" VARD_fscore_0.5_threshold_0="mettle" VARD_fscore_0.5_threshold_25="mettle" VARD_fscore_0.5_threshold_50="mettle" VARD_fscore_1.0_threshold_0="mettle" VARD_fscore_1.0_threshold_25="mettle" VARD_fscore_1.0_threshold_50="mettle" VARD_fscore_2.0_threshold_0="mettle" VARD_fscore_2.0_threshold_25="mettle" VARD_fscore_2.0_threshold_50="mettle">meddel</word>
    <word word_id="SB_J_604.5.123">with</word>
    <word word_id="SB_J_604.5.124" VARD_fscore_0.1_threshold_0="any" VARD_fscore_0.1_threshold_25="any" VARD_fscore_0.5_threshold_0="any" VARD_fscore_0.5_threshold_25="any" VARD_fscore_0.5_threshold_50="any" VARD_fscore_1.0_threshold_0="any" VARD_fscore_1.0_threshold_25="any" VARD_fscore_2.0_threshold_0="any" VARD_fscore_2.0_threshold_25="any" VARD_fscore_2.0_threshold_50="any">anny</word>
    <word word_id="SB_J_604.5.125">but</word>
    <word word_id="SB_J_604.5.126" VARD_fscore_0.1_threshold_0="Lindens," VARD_fscore_0.5_threshold_0="Lindens," VARD_fscore_0.5_threshold_25="Lindens," VARD_fscore_1.0_threshold_0="Lindens," VARD_fscore_2.0_threshold_0="Lindens,">Londons,</word>
    <word word_id="SB_J_604.5.127">and</word>
    <word word_id="SB_J_604.5.128" VARD_fscore_0.1_threshold_0="mine" VARD_fscore_0.1_threshold_25="mine" VARD_fscore_0.1_threshold_50="mine" VARD_fscore_0.5_threshold_0="mine" VARD_fscore_0.5_threshold_25="mine" VARD_fscore_0.5_threshold_50="mine" VARD_fscore_0.5_threshold_75="mine" VARD_fscore_1.0_threshold_0="mine" VARD_fscore_1.0_threshold_25="mine" VARD_fscore_1.0_threshold_50="mine" VARD_fscore_2.0_threshold_0="mine" VARD_fscore_2.0_threshold_25="mine" VARD_fscore_2.0_threshold_50="mine" VARD_fscore_2.0_threshold_75="mine">myne</word>
    <word word_id="SB_J_604.5.129">old</word>
    <word word_id="SB_J_604.5.130">customers</word>
    <word word_id="SB_J_604.5.131">here,</word>
    <word word_id="SB_J_604.5.132">and</word>
    <word word_id="SB_J_604.5.133" VARD_fscore_0.1_threshold_0="that" VARD_fscore_0.5_threshold_0="that" VARD_fscore_0.5_threshold_25="that" VARD_fscore_1.0_threshold_0="that" VARD_fscore_2.0_threshold_0="that">thet</word>
    <word word_id="SB_J_604.5.134" VARD_fscore_0.1_threshold_0="so" VARD_fscore_0.1_threshold_25="so" VARD_fscore_0.1_threshold_50="so" VARD_fscore_0.5_threshold_0="so" VARD_fscore_0.5_threshold_25="so" VARD_fscore_0.5_threshold_50="so" VARD_fscore_1.0_threshold_0="so" VARD_fscore_1.0_threshold_25="so" VARD_fscore_1.0_threshold_50="so" VARD_fscore_2.0_threshold_0="so" VARD_fscore_2.0_threshold_25="so" VARD_fscore_2.0_threshold_50="so">soo</word>
    <word word_id="SB_J_604.5.135" VARD_fscore_0.1_threshold_0="little" VARD_fscore_0.1_threshold_25="little" VARD_fscore_0.1_threshold_50="little" VARD_fscore_0.5_threshold_0="little" VARD_fscore_0.5_threshold_25="little" VARD_fscore_0.5_threshold_50="little" VARD_fscore_1.0_threshold_0="little" VARD_fscore_1.0_threshold_25="little" VARD_fscore_1.0_threshold_50="little" VARD_fscore_2.0_threshold_0="little" VARD_fscore_2.0_threshold_25="little" VARD_fscore_2.0_threshold_50="little">lyttill</word>
    <word word_id="SB_J_604.5.136">as</word>
    <word word_id="SB_J_604.5.137">I</word>
    <word word_id="SB_J_604.5.138" VARD_fscore_0.1_threshold_0="may." VARD_fscore_0.1_threshold_25="may." VARD_fscore_0.1_threshold_50="may." VARD_fscore_0.5_threshold_0="may." VARD_fscore_0.5_threshold_25="may." VARD_fscore_0.5_threshold_50="may." VARD_fscore_0.5_threshold_75="may." VARD_fscore_1.0_threshold_0="may." VARD_fscore_1.0_threshold_25="may." VARD_fscore_1.0_threshold_50="may." VARD_fscore_2.0_threshold_0="may." VARD_fscore_2.0_threshold_25="may." VARD_fscore_2.0_threshold_50="may." VARD_fscore_2.0_threshold_75="may.">maye.</word>
    <word word_id="SB_J_604.6.0">I</word>
    <word word_id="SB_J_604.6.1" VARD_fscore_0.1_threshold_0="wold" VARD_fscore_0.1_threshold_25="wold" VARD_fscore_0.5_threshold_0="wold" VARD_fscore_0.5_threshold_25="wold" VARD_fscore_0.5_threshold_50="wold" VARD_fscore_1.0_threshold_0="wold" VARD_fscore_1.0_threshold_25="wold" VARD_fscore_2.0_threshold_0="wold" VARD_fscore_2.0_threshold_25="wold" VARD_fscore_2.0_threshold_50="wold">wolld</word>
    <word word_id="SB_J_604.6.2" VARD_fscore_0.1_threshold_0="desire" VARD_fscore_0.1_threshold_25="desire" VARD_fscore_0.1_threshold_50="desire" VARD_fscore_0.5_threshold_0="desire" VARD_fscore_0.5_threshold_25="desire" VARD_fscore_0.5_threshold_50="desire" VARD_fscore_0.5_threshold_75="desire" VARD_fscore_1.0_threshold_0="desire" VARD_fscore_1.0_threshold_25="desire" VARD_fscore_1.0_threshold_50="desire" VARD_fscore_2.0_threshold_0="desire" VARD_fscore_2.0_threshold_25="desire" VARD_fscore_2.0_threshold_50="desire" VARD_fscore_2.0_threshold_75="desire">desyre</word>
    <word word_id="SB_J_604.6.3" VARD_fscore_0.1_threshold_0="you" VARD_fscore_0.1_threshold_25="you" VARD_fscore_0.1_threshold_50="you" VARD_fscore_0.5_threshold_0="you" VARD_fscore_0.5_threshold_25="you" VARD_fscore_0.5_threshold_50="you" VARD_fscore_0.5_threshold_75="you" VARD_fscore_1.0_threshold_0="you" VARD_fscore_1.0_threshold_25="you" VARD_fscore_1.0_threshold_50="you" VARD_fscore_2.0_threshold_0="you" VARD_fscore_2.0_threshold_25="you" VARD_fscore_2.0_threshold_50="you" VARD_fscore_2.0_threshold_75="you">youe</word>
    <word word_id="SB_J_604.6.4" VARD_fscore_0.1_threshold_0="if" VARD_fscore_0.1_threshold_25="if" VARD_fscore_0.1_threshold_50="if" VARD_fscore_0.5_threshold_0="if" VARD_fscore_0.5_threshold_25="if" VARD_fscore_0.5_threshold_50="if" VARD_fscore_0.5_threshold_75="if" VARD_fscore_1.0_threshold_0="if" VARD_fscore_1.0_threshold_25="if" VARD_fscore_1.0_threshold_50="if" VARD_fscore_2.0_threshold_0="if" VARD_fscore_2.0_threshold_25="if" VARD_fscore_2.0_threshold_50="if" VARD_fscore_2.0_threshold_75="if">yf</word>
    <word word_id="SB_J_604.6.5" VARD_fscore_0.1_threshold_0="any" VARD_fscore_0.1_threshold_25="any" VARD_fscore_0.5_threshold_0="any" VARD_fscore_0.5_threshold_25="any" VARD_fscore_0.5_threshold_50="any" VARD_fscore_1.0_threshold_0="any" VARD_fscore_1.0_threshold_25="any" VARD_fscore_2.0_threshold_0="any" VARD_fscore_2.0_threshold_25="any" VARD_fscore_2.0_threshold_50="any">anny</word>
    <word word_id="SB_J_604.6.6" VARD_fscore_0.1_threshold_0="friend" VARD_fscore_0.1_threshold_25="friend" VARD_fscore_0.1_threshold_50="friend" VARD_fscore_0.5_threshold_0="friend" VARD_fscore_0.5_threshold_25="friend" VARD_fscore_0.5_threshold_50="friend" VARD_fscore_1.0_threshold_0="friend" VARD_fscore_1.0_threshold_25="friend" VARD_fscore_1.0_threshold_50="friend" VARD_fscore_2.0_threshold_0="friend" VARD_fscore_2.0_threshold_25="friend" VARD_fscore_2.0_threshold_50="friend">frynd</word>
    <word word_id="SB_J_604.6.7">of</word>
    <word word_id="SB_J_604.6.8" VARD_fscore_0.1_threshold_0="yours" VARD_fscore_0.1_threshold_25="yours" VARD_fscore_0.1_threshold_50="yours" VARD_fscore_0.5_threshold_0="yours" VARD_fscore_0.5_threshold_25="yours" VARD_fscore_0.5_threshold_50="yours" VARD_fscore_0.5_threshold_75="yours" VARD_fscore_1.0_threshold_0="yours" VARD_fscore_1.0_threshold_25="yours" VARD_fscore_1.0_threshold_50="yours" VARD_fscore_2.0_threshold_0="yours" VARD_fscore_2.0_threshold_25="yours" VARD_fscore_2.0_threshold_50="yours" VARD_fscore_2.0_threshold_75="yours">youres</word>
    <word word_id="SB_J_604.6.9">goo</word>
    <word word_id="SB_J_604.6.10">to</word>
    <word word_id="SB_J_604.6.11">Lyn,</word>
    <word word_id="SB_J_604.6.12">and</word>
    <word word_id="SB_J_604.6.13" VARD_fscore_0.1_threshold_0="wainscots" VARD_fscore_0.1_threshold_25="wainscots" VARD_fscore_0.5_threshold_0="wainscots" VARD_fscore_0.5_threshold_25="wainscots" VARD_fscore_1.0_threshold_0="wainscots" VARD_fscore_1.0_threshold_25="wainscots" VARD_fscore_2.0_threshold_0="wainscots" VARD_fscore_2.0_threshold_25="wainscots">waynskotes</word>
    <word word_id="SB_J_604.6.14">there</word>
    <word word_id="SB_J_604.6.15">be</word>
    <word word_id="SB_J_604.6.16">to</word>
    <word word_id="SB_J_604.6.17">be</word>
    <word word_id="SB_J_604.6.18">had</word>
    <word word_id="SB_J_604.6.19">for</word>
    <word word_id="SB_J_604.6.20" VARD_fscore_0.1_threshold_0="icily" VARD_fscore_0.5_threshold_0="icily" VARD_fscore_1.0_threshold_0="icily" VARD_fscore_2.0_threshold_0="icily">iiijli</word>
    <word word_id="SB_J_604.6.21">or</word>
    <word word_id="SB_J_604.6.22" VARD_fscore_0.1_threshold_0="thereabouts" VARD_fscore_0.1_threshold_25="thereabouts" VARD_fscore_0.1_threshold_50="thereabouts" VARD_fscore_0.5_threshold_0="thereabouts" VARD_fscore_0.5_threshold_25="thereabouts" VARD_fscore_0.5_threshold_50="thereabouts" VARD_fscore_1.0_threshold_0="thereabouts" VARD_fscore_1.0_threshold_25="thereabouts" VARD_fscore_1.0_threshold_50="thereabouts" VARD_fscore_2.0_threshold_0="thereabouts" VARD_fscore_2.0_threshold_25="thereabouts" VARD_fscore_2.0_threshold_50="thereabouts">thereabowtes</word>
    <word word_id="SB_J_604.6.23">that</word>
    <word word_id="SB_J_604.6.24">be</word>
    <word word_id="SB_J_604.6.25">good,</word>
    <word word_id="SB_J_604.6.26">I</word>
    <word word_id="SB_J_604.6.27" VARD_fscore_0.1_threshold_0="wold" VARD_fscore_0.1_threshold_25="wold" VARD_fscore_0.5_threshold_0="wold" VARD_fscore_0.5_threshold_25="wold" VARD_fscore_0.5_threshold_50="wold" VARD_fscore_1.0_threshold_0="wold" VARD_fscore_1.0_threshold_25="wold" VARD_fscore_2.0_threshold_0="wold" VARD_fscore_2.0_threshold_25="wold" VARD_fscore_2.0_threshold_50="wold">wolld</word>
    <word word_id="SB_J_604.6.28">with</word>
    <word word_id="SB_J_604.6.29" VARD_fscore_0.1_threshold_0="some" VARD_fscore_0.1_threshold_25="some" VARD_fscore_0.1_threshold_50="some" VARD_fscore_0.5_threshold_0="some" VARD_fscore_0.5_threshold_25="some" VARD_fscore_0.5_threshold_50="some" VARD_fscore_0.5_threshold_75="some" VARD_fscore_1.0_threshold_0="some" VARD_fscore_1.0_threshold_25="some" VARD_fscore_1.0_threshold_50="some" VARD_fscore_2.0_threshold_0="some" VARD_fscore_2.0_threshold_25="some" VARD_fscore_2.0_threshold_50="some" VARD_fscore_2.0_threshold_75="some">som</word>
    <word word_id="SB_J_604.6.30" VARD_fscore_0.1_threshold_0="honest" VARD_fscore_0.1_threshold_25="honest" VARD_fscore_0.1_threshold_50="honest" VARD_fscore_0.5_threshold_0="honest" VARD_fscore_0.5_threshold_25="honest" VARD_fscore_0.5_threshold_50="honest" VARD_fscore_0.5_threshold_75="honest" VARD_fscore_1.0_threshold_0="honest" VARD_fscore_1.0_threshold_25="honest" VARD_fscore_1.0_threshold_50="honest" VARD_fscore_2.0_threshold_0="honest" VARD_fscore_2.0_threshold_25="honest" VARD_fscore_2.0_threshold_50="honest" VARD_fscore_2.0_threshold_75="honest">honnest</word>
    <word word_id="SB_J_604.6.31">man</word>
    <word word_id="SB_J_604.6.32">that</word>
    <word word_id="SB_J_604.6.33" VARD_fscore_0.1_threshold_0="could" VARD_fscore_0.1_threshold_25="could" VARD_fscore_0.1_threshold_50="could" VARD_fscore_0.5_threshold_0="could" VARD_fscore_0.5_threshold_25="could" VARD_fscore_0.5_threshold_50="could" VARD_fscore_1.0_threshold_0="could" VARD_fscore_1.0_threshold_25="could" VARD_fscore_1.0_threshold_50="could" VARD_fscore_2.0_threshold_0="could" VARD_fscore_2.0_threshold_25="could" VARD_fscore_2.0_threshold_50="could">cowlld</word>
    <word word_id="SB_J_604.6.34" VARD_fscore_0.1_threshold_0="cheese" VARD_fscore_0.5_threshold_0="cheese" VARD_fscore_1.0_threshold_0="cheese" VARD_fscore_2.0_threshold_0="cheese">ciewse</word>
    <word word_id="SB_J_604.6.35">them</word>
    <word word_id="SB_J_604.6.36">have</word>
    <word word_id="SB_J_604.6.37">an</word>
    <word word_id="SB_J_604.6.38">C</word>
    <word word_id="SB_J_604.6.39">that</word>
    <word word_id="SB_J_604.6.40" VARD_fscore_0.1_threshold_0="is" VARD_fscore_0.1_threshold_25="is" VARD_fscore_0.1_threshold_50="is" VARD_fscore_0.5_threshold_0="is" VARD_fscore_0.5_threshold_25="is" VARD_fscore_0.5_threshold_50="is" VARD_fscore_0.5_threshold_75="is" VARD_fscore_1.0_threshold_0="is" VARD_fscore_1.0_threshold_25="is" VARD_fscore_1.0_threshold_50="is" VARD_fscore_2.0_threshold_0="is" VARD_fscore_2.0_threshold_25="is" VARD_fscore_2.0_threshold_50="is" VARD_fscore_2.0_threshold_75="is">ys</word>
    <word word_id="SB_J_604.6.41">good,</word>
    <word word_id="SB_J_604.6.42">to</word>
    <word word_id="SB_J_604.6.43">be</word>
    <word word_id="SB_J_604.6.44">sent</word>
    <word word_id="SB_J_604.6.45">to</word>
    <word word_id="SB_J_604.6.46">......</word>
    <word word_id="SB_J_604.6.47">soon,</word>
    <word word_id="SB_J_604.6.48">but</word>
    <word word_id="SB_J_604.6.49">I</word>
    <word word_id="SB_J_604.6.50">wold</word>
    <word word_id="SB_J_604.6.51">be</word>
    <word word_id="SB_J_604.6.52" VARD_fscore_0.1_threshold_0="sour" VARD_fscore_0.1_threshold_25="sour" VARD_fscore_0.1_threshold_50="sour" VARD_fscore_0.5_threshold_0="sour" VARD_fscore_0.5_threshold_25="sour" VARD_fscore_0.5_threshold_50="sour" VARD_fscore_1.0_threshold_0="sour" VARD_fscore_1.0_threshold_25="sour" VARD_fscore_1.0_threshold_50="sour" VARD_fscore_2.0_threshold_0="sour" VARD_fscore_2.0_threshold_25="sour" VARD_fscore_2.0_threshold_50="sour">sewr</word>
    <word word_id="SB_J_604.6.53">of</word>
    <word word_id="SB_J_604.6.54">them</word>
    <word word_id="SB_J_604.6.55" VARD_fscore_0.1_threshold_0="now." VARD_fscore_0.1_threshold_25="now." VARD_fscore_0.1_threshold_50="now." VARD_fscore_0.5_threshold_0="now." VARD_fscore_0.5_threshold_25="now." VARD_fscore_0.5_threshold_50="now." VARD_fscore_0.5_threshold_75="now." VARD_fscore_1.0_threshold_0="now." VARD_fscore_1.0_threshold_25="now." VARD_fscore_1.0_threshold_50="now." VARD_fscore_2.0_threshold_0="now." VARD_fscore_2.0_threshold_25="now." VARD_fscore_2.0_threshold_50="now." VARD_fscore_2.0_threshold_75="now.">nowe.</word>
    <word word_id="SB_J_604.6.56">But</word>
    <word word_id="SB_J_604.6.57">so</word>
    <word word_id="SB_J_604.6.58">they</word>
    <word word_id="SB_J_604.6.59">be</word>
    <word word_id="SB_J_604.6.60">there</word>
    <word word_id="SB_J_604.6.61" VARD_fscore_0.1_threshold_0="before" VARD_fscore_0.5_threshold_0="before" VARD_fscore_0.5_threshold_25="before" VARD_fscore_1.0_threshold_0="before" VARD_fscore_2.0_threshold_0="before">beffore</word>
    <word word_id="SB_J_604.6.62" VARD_fscore_0.1_threshold_0="Easter" VARD_fscore_0.1_threshold_25="Easter" VARD_fscore_0.5_threshold_0="Easter" VARD_fscore_0.5_threshold_25="Easter" VARD_fscore_0.5_threshold_50="Easter" VARD_fscore_1.0_threshold_0="Easter" VARD_fscore_1.0_threshold_25="Easter" VARD_fscore_2.0_threshold_0="Easter" VARD_fscore_2.0_threshold_25="Easter" VARD_fscore_2.0_threshold_50="Easter">Eester</word>
    <word word_id="SB_J_604.6.63">or</word>
    <word word_id="SB_J_604.6.64">a</word>
    <word word_id="SB_J_604.6.65" VARD_fscore_0.1_threshold_0="monies" VARD_fscore_0.1_threshold_25="monies" VARD_fscore_0.5_threshold_0="monies" VARD_fscore_0.5_threshold_25="monies" VARD_fscore_1.0_threshold_0="monies" VARD_fscore_1.0_threshold_25="monies" VARD_fscore_2.0_threshold_0="monies" VARD_fscore_2.0_threshold_25="monies">monnyth</word>
    <word word_id="SB_J_604.6.66" VARD_fscore_0.1_threshold_0="after," VARD_fscore_0.5_threshold_0="after," VARD_fscore_0.5_threshold_25="after," VARD_fscore_1.0_threshold_0="after," VARD_fscore_2.0_threshold_0="after,">affter,</word>
    <word word_id="SB_J_604.6.67">so</word>
    <word word_id="SB_J_604.6.68">I</word>
    <word word_id="SB_J_604.6.69">may</word>
    <word word_id="SB_J_604.6.70">be</word>
    <word word_id="SB_J_604.6.71">there</word>
    <word word_id="SB_J_604.6.72">well</word>
    <word word_id="SB_J_604.6.73" VARD_fscore_0.1_threshold_0="served," VARD_fscore_0.1_threshold_25="served," VARD_fscore_0.1_threshold_50="served," VARD_fscore_0.5_threshold_0="served," VARD_fscore_0.5_threshold_25="served," VARD_fscore_0.5_threshold_50="served," VARD_fscore_1.0_threshold_0="served," VARD_fscore_1.0_threshold_25="served," VARD_fscore_1.0_threshold_50="served," VARD_fscore_2.0_threshold_0="served," VARD_fscore_2.0_threshold_25="served," VARD_fscore_2.0_threshold_50="served,">servyd,</word>
    <word word_id="SB_J_604.6.74">I</word>
    <word word_id="SB_J_604.6.75" VARD_fscore_0.1_threshold_0="shall" VARD_fscore_0.1_threshold_25="shall" VARD_fscore_0.1_threshold_50="shall" VARD_fscore_0.5_threshold_0="shall" VARD_fscore_0.5_threshold_25="shall" VARD_fscore_0.5_threshold_50="shall" VARD_fscore_1.0_threshold_0="shall" VARD_fscore_1.0_threshold_25="shall" VARD_fscore_1.0_threshold_50="shall" VARD_fscore_2.0_threshold_0="shall" VARD_fscore_2.0_threshold_25="shall" VARD_fscore_2.0_threshold_50="shall">shal</word>
    <word word_id="SB_J_604.6.76">be</word>
    <word word_id="SB_J_604.6.77">content.</word>
    <word word_id="SB_J_604.6.78">Thus</word>
    <word word_id="SB_J_604.6.79">having</word>
    <word word_id="SB_J_604.6.80">non</word>
    <word word_id="SB_J_604.6.81" VARD_fscore_0.1_threshold_0="nephews" VARD_fscore_0.1_threshold_25="nephews" VARD_fscore_0.1_threshold_50="nephews" VARD_fscore_0.5_threshold_0="nephews" VARD_fscore_0.5_threshold_25="nephews" VARD_fscore_0.5_threshold_50="nephews" VARD_fscore_1.0_threshold_0="nephews" VARD_fscore_1.0_threshold_25="nephews" VARD_fscore_1.0_threshold_50="nephews" VARD_fscore_2.0_threshold_0="nephews" VARD_fscore_2.0_threshold_25="nephews" VARD_fscore_2.0_threshold_50="nephews">newys</word>
    <word word_id="SB_J_604.6.82" VARD_fscore_0.1_threshold_0="worth" VARD_fscore_0.1_threshold_25="worth" VARD_fscore_0.1_threshold_50="worth" VARD_fscore_0.5_threshold_0="worth" VARD_fscore_0.5_threshold_25="worth" VARD_fscore_0.5_threshold_50="worth" VARD_fscore_0.5_threshold_75="worth" VARD_fscore_1.0_threshold_0="worth" VARD_fscore_1.0_threshold_25="worth" VARD_fscore_1.0_threshold_50="worth" VARD_fscore_2.0_threshold_0="worth" VARD_fscore_2.0_threshold_25="worth" VARD_fscore_2.0_threshold_50="worth" VARD_fscore_2.0_threshold_75="worth">worthe</word>
    <word word_id="SB_J_604.6.83" VARD_fscore_0.1_threshold_0="writing," VARD_fscore_0.1_threshold_25="writing," VARD_fscore_0.1_threshold_50="writing," VARD_fscore_0.5_threshold_0="writing," VARD_fscore_0.5_threshold_25="writing," VARD_fscore_0.5_threshold_50="writing," VARD_fscore_1.0_threshold_0="writing," VARD_fscore_1.0_threshold_25="writing," VARD_fscore_1.0_threshold_50="writing," VARD_fscore_2.0_threshold_0="writing," VARD_fscore_2.0_threshold_25="writing," VARD_fscore_2.0_threshold_50="writing,">writtyng,</word>
    <word word_id="SB_J_604.6.84" VARD_fscore_0.1_threshold_0="commit" VARD_fscore_0.1_threshold_25="commit" VARD_fscore_0.1_threshold_50="commit" VARD_fscore_0.5_threshold_0="commit" VARD_fscore_0.5_threshold_25="commit" VARD_fscore_0.5_threshold_50="commit" VARD_fscore_0.5_threshold_75="commit" VARD_fscore_1.0_threshold_0="commit" VARD_fscore_1.0_threshold_25="commit" VARD_fscore_1.0_threshold_50="commit" VARD_fscore_2.0_threshold_0="commit" VARD_fscore_2.0_threshold_25="commit" VARD_fscore_2.0_threshold_50="commit" VARD_fscore_2.0_threshold_75="commit">commyt</word>
    <word word_id="SB_J_604.6.85" VARD_fscore_0.1_threshold_0="you" VARD_fscore_0.1_threshold_25="you" VARD_fscore_0.1_threshold_50="you" VARD_fscore_0.5_threshold_0="you" VARD_fscore_0.5_threshold_25="you" VARD_fscore_0.5_threshold_50="you" VARD_fscore_0.5_threshold_75="you" VARD_fscore_1.0_threshold_0="you" VARD_fscore_1.0_threshold_25="you" VARD_fscore_1.0_threshold_50="you" VARD_fscore_2.0_threshold_0="you" VARD_fscore_2.0_threshold_25="you" VARD_fscore_2.0_threshold_50="you" VARD_fscore_2.0_threshold_75="you">youe</word>
    <word word_id="SB_J_604.6.86">and</word>
    <word word_id="SB_J_604.6.87">all</word>
    <word word_id="SB_J_604.6.88" VARD_fscore_0.1_threshold_0="yours" VARD_fscore_0.1_threshold_25="yours" VARD_fscore_0.1_threshold_50="yours" VARD_fscore_0.5_threshold_0="yours" VARD_fscore_0.5_threshold_25="yours" VARD_fscore_0.5_threshold_50="yours" VARD_fscore_0.5_threshold_75="yours" VARD_fscore_1.0_threshold_0="yours" VARD_fscore_1.0_threshold_25="yours" VARD_fscore_1.0_threshold_50="yours" VARD_fscore_2.0_threshold_0="yours" VARD_fscore_2.0_threshold_25="yours" VARD_fscore_2.0_threshold_50="yours" VARD_fscore_2.0_threshold_75="yours">youres</word>
    <word word_id="SB_J_604.6.89">to</word>
    <word word_id="SB_J_604.6.90">the</word>
    <word word_id="SB_J_604.6.91" VARD_fscore_0.1_threshold_0="Living" VARD_fscore_0.1_threshold_25="Living" VARD_fscore_0.1_threshold_50="Living" VARD_fscore_0.5_threshold_0="Living" VARD_fscore_0.5_threshold_25="Living" VARD_fscore_0.5_threshold_50="Living" VARD_fscore_1.0_threshold_0="Living" VARD_fscore_1.0_threshold_25="Living" VARD_fscore_1.0_threshold_50="Living" VARD_fscore_2.0_threshold_0="Living" VARD_fscore_2.0_threshold_25="Living" VARD_fscore_2.0_threshold_50="Living">Lyvyng</word>
    <word word_id="SB_J_604.6.92" VARD_fscore_0.1_threshold_0="Eternal" VARD_fscore_0.1_threshold_25="Eternal" VARD_fscore_0.1_threshold_50="Eternal" VARD_fscore_0.5_threshold_0="Eternal" VARD_fscore_0.5_threshold_25="Eternal" VARD_fscore_0.5_threshold_50="Eternal" VARD_fscore_0.5_threshold_75="Eternal" VARD_fscore_1.0_threshold_0="Eternal" VARD_fscore_1.0_threshold_25="Eternal" VARD_fscore_1.0_threshold_50="Eternal" VARD_fscore_2.0_threshold_0="Eternal" VARD_fscore_2.0_threshold_25="Eternal" VARD_fscore_2.0_threshold_50="Eternal" VARD_fscore_2.0_threshold_75="Eternal">Eternall</word>
    <word word_id="SB_J_604.6.93">Lord,</word>
    <word word_id="SB_J_604.6.94" VARD_fscore_0.1_threshold_0="Whoa" VARD_fscore_0.5_threshold_0="Whoa" VARD_fscore_0.5_threshold_25="Whoa" VARD_fscore_1.0_threshold_0="Whoa" VARD_fscore_2.0_threshold_0="Whoa">Whoo</word>
    <word word_id="SB_J_604.6.95">send</word>
    <word word_id="SB_J_604.6.96">us</word>
    <word word_id="SB_J_604.6.97">His</word>
    <word word_id="SB_J_604.6.98" VARD_fscore_0.1_threshold_0="peak," VARD_fscore_0.5_threshold_0="peak," VARD_fscore_1.0_threshold_0="peak," VARD_fscore_2.0_threshold_0="peak,">peax,</word>
    <word word_id="SB_J_604.6.99">and</word>
    <word word_id="SB_J_604.6.100">grace</word>
    <word word_id="SB_J_604.6.101">to</word>
    <word word_id="SB_J_604.6.102">do</word>
    <word word_id="SB_J_604.6.103">His</word>
    <word word_id="SB_J_604.6.104">will.</word>
    <word word_id="SB_J_604.6.105">In</word>
    <word word_id="SB_J_604.6.106" VARD_fscore_0.1_threshold_0="much" VARD_fscore_0.1_threshold_25="much" VARD_fscore_0.1_threshold_50="much" VARD_fscore_0.5_threshold_0="much" VARD_fscore_0.5_threshold_25="much" VARD_fscore_0.5_threshold_50="much" VARD_fscore_0.5_threshold_75="much" VARD_fscore_1.0_threshold_0="much" VARD_fscore_1.0_threshold_25="much" VARD_fscore_1.0_threshold_50="much" VARD_fscore_2.0_threshold_0="much" VARD_fscore_2.0_threshold_25="much" VARD_fscore_2.0_threshold_50="much" VARD_fscore_2.0_threshold_75="much">moche</word>
    <word word_id="SB_J_604.6.107" VARD_fscore_0.1_threshold_0="hoist" VARD_fscore_0.1_threshold_25="hoist" VARD_fscore_0.5_threshold_0="hoist" VARD_fscore_0.5_threshold_25="hoist" VARD_fscore_0.5_threshold_50="hoist" VARD_fscore_1.0_threshold_0="hoist" VARD_fscore_1.0_threshold_25="hoist" VARD_fscore_2.0_threshold_0="hoist" VARD_fscore_2.0_threshold_25="hoist">haest</word>
    <word word_id="SB_J_604.6.108" VARD_fscore_0.1_threshold_0="scribbled." VARD_fscore_0.1_threshold_25="scribbled." VARD_fscore_0.5_threshold_0="scribbled." VARD_fscore_0.5_threshold_25="scribbled." VARD_fscore_1.0_threshold_0="scribbled." VARD_fscore_1.0_threshold_25="scribbled." VARD_fscore_2.0_threshold_0="scribbled." VARD_fscore_2.0_threshold_25="scribbled.">skribled.</word>
    <word word_id="SB_J_604.7.0">By</word>
    <word word_id="SB_J_604.7.1" VARD_fscore_0.1_threshold_0="yours," VARD_fscore_0.1_threshold_25="yours," VARD_fscore_0.1_threshold_50="yours," VARD_fscore_0.5_threshold_0="yours," VARD_fscore_0.5_threshold_25="yours," VARD_fscore_0.5_threshold_50="yours," VARD_fscore_0.5_threshold_75="yours," VARD_fscore_1.0_threshold_0="yours," VARD_fscore_1.0_threshold_25="yours," VARD_fscore_1.0_threshold_50="yours," VARD_fscore_2.0_threshold_0="yours," VARD_fscore_2.0_threshold_25="yours," VARD_fscore_2.0_threshold_50="yours," VARD_fscore_2.0_threshold_75="yours,">youres,</word>
    <word word_id="SB_J_604.8.0">Antony</word>
    <word word_id="SB_J_604.8.1">Cave.</word>
    <word word_id="SB_J_604.9.0"/>
    <word word_id="SB_J_604.10.0">Add.</word>
    <word word_id="SB_J_604.10.1">To</word>
    <word word_id="SB_J_604.10.2">his</word>
    <word word_id="SB_J_604.10.3" VARD_fscore_0.1_threshold_0="very" VARD_fscore_0.1_threshold_25="very" VARD_fscore_0.1_threshold_50="very" VARD_fscore_0.5_threshold_0="very" VARD_fscore_0.5_threshold_25="very" VARD_fscore_0.5_threshold_50="very" VARD_fscore_0.5_threshold_75="very" VARD_fscore_1.0_threshold_0="very" VARD_fscore_1.0_threshold_25="very" VARD_fscore_1.0_threshold_50="very" VARD_fscore_2.0_threshold_0="very" VARD_fscore_2.0_threshold_25="very" VARD_fscore_2.0_threshold_50="very" VARD_fscore_2.0_threshold_75="very">verry</word>
    <word word_id="SB_J_604.10.4" VARD_fscore_0.1_threshold_0="loving" VARD_fscore_0.1_threshold_25="loving" VARD_fscore_0.1_threshold_50="loving" VARD_fscore_0.5_threshold_0="loving" VARD_fscore_0.5_threshold_25="loving" VARD_fscore_0.5_threshold_50="loving" VARD_fscore_1.0_threshold_0="loving" VARD_fscore_1.0_threshold_25="loving" VARD_fscore_1.0_threshold_50="loving" VARD_fscore_2.0_threshold_0="loving" VARD_fscore_2.0_threshold_25="loving" VARD_fscore_2.0_threshold_50="loving">lovinge</word>
    <word word_id="SB_J_604.10.5">....................</word>
    <word word_id="SB_J_604.11.0">End.</word>
    <word word_id="SB_J_604.11.1">1548,</word>
    <word word_id="SB_J_604.11.2">from</word>
    <word word_id="SB_J_604.11.3">my</word>
    <word word_id="SB_J_604.11.4" VARD_fscore_0.1_threshold_0="uncle" VARD_fscore_0.5_threshold_0="uncle" VARD_fscore_0.5_threshold_25="uncle" VARD_fscore_1.0_threshold_0="uncle" VARD_fscore_2.0_threshold_0="uncle">oncle</word>
    <word word_id="SB_J_604.11.5">Mr.</word>
    <word word_id="SB_J_604.11.6">Anthony</word>
    <word word_id="SB_J_604.11.7">Cave,</word>
    <word word_id="SB_J_604.11.8">le</word>
    <word word_id="SB_J_604.11.9">1</word>
    <word word_id="SB_J_604.11.10" VARD_fscore_0.1_threshold_0="December," VARD_fscore_0.1_threshold_25="December," VARD_fscore_0.1_threshold_50="December," VARD_fscore_0.5_threshold_0="December," VARD_fscore_0.5_threshold_25="December," VARD_fscore_0.5_threshold_50="December," VARD_fscore_1.0_threshold_0="December," VARD_fscore_1.0_threshold_25="December," VARD_fscore_1.0_threshold_50="December," VARD_fscore_2.0_threshold_0="December," VARD_fscore_2.0_threshold_25="December," VARD_fscore_2.0_threshold_50="December,">Desember,</word>
    <word word_id="SB_J_604.11.11" VARD_fscore_0.1_threshold_0="concerning" VARD_fscore_0.1_threshold_25="concerning" VARD_fscore_0.1_threshold_50="concerning" VARD_fscore_0.5_threshold_0="concerning" VARD_fscore_0.5_threshold_25="concerning" VARD_fscore_0.5_threshold_50="concerning" VARD_fscore_1.0_threshold_0="concerning" VARD_fscore_1.0_threshold_25="concerning" VARD_fscore_1.0_threshold_50="concerning" VARD_fscore_2.0_threshold_0="concerning" VARD_fscore_2.0_threshold_25="concerning" VARD_fscore_2.0_threshold_50="concerning">conserning</word>
    <word word_id="SB_J_604.11.12">candle</word>
    <word word_id="SB_J_604.11.13">he</word>
    <word word_id="SB_J_604.11.14" VARD_fscore_0.1_threshold_0="sends" VARD_fscore_0.1_threshold_25="sends" VARD_fscore_0.1_threshold_50="sends" VARD_fscore_0.5_threshold_0="sends" VARD_fscore_0.5_threshold_25="sends" VARD_fscore_0.5_threshold_50="sends" VARD_fscore_1.0_threshold_0="sends" VARD_fscore_1.0_threshold_25="sends" VARD_fscore_1.0_threshold_50="sends" VARD_fscore_2.0_threshold_0="sends" VARD_fscore_2.0_threshold_25="sends" VARD_fscore_2.0_threshold_50="sends">sendith</word>
    <word word_id="SB_J_604.11.15">for,</word>
    <word word_id="SB_J_604.11.16">for</word>
    <word word_id="SB_J_604.11.17">which</word>
    <word word_id="SB_J_604.11.18">he</word>
    <word word_id="SB_J_604.11.19" VARD_fscore_0.1_threshold_0="wills" VARD_fscore_0.1_threshold_25="wills" VARD_fscore_0.1_threshold_50="wills" VARD_fscore_0.5_threshold_0="wills" VARD_fscore_0.5_threshold_25="wills" VARD_fscore_0.5_threshold_50="wills" VARD_fscore_0.5_threshold_75="wills" VARD_fscore_1.0_threshold_0="wills" VARD_fscore_1.0_threshold_25="wills" VARD_fscore_1.0_threshold_50="wills" VARD_fscore_2.0_threshold_0="wills" VARD_fscore_2.0_threshold_25="wills" VARD_fscore_2.0_threshold_50="wills">willeth</word>
    <word word_id="SB_J_604.11.20">me</word>
    <word word_id="SB_J_604.11.21">to</word>
    <word word_id="SB_J_604.11.22" VARD_fscore_0.1_threshold_0="answer" VARD_fscore_0.1_threshold_25="answer" VARD_fscore_0.1_threshold_50="answer" VARD_fscore_0.5_threshold_0="answer" VARD_fscore_0.5_threshold_25="answer" VARD_fscore_0.5_threshold_50="answer" VARD_fscore_0.5_threshold_75="answer" VARD_fscore_1.0_threshold_0="answer" VARD_fscore_1.0_threshold_25="answer" VARD_fscore_1.0_threshold_50="answer" VARD_fscore_2.0_threshold_0="answer" VARD_fscore_2.0_threshold_25="answer" VARD_fscore_2.0_threshold_50="answer" VARD_fscore_2.0_threshold_75="answer">aunswer</word>
    <word word_id="SB_J_604.11.23">Morton;</word>
    <word word_id="SB_J_604.11.24">of</word>
    <word word_id="SB_J_604.11.25">xxli</word>
    <word word_id="SB_J_604.11.26">on</word>
    <word word_id="SB_J_604.11.27" VARD_fscore_0.1_threshold_0="fellas" VARD_fscore_0.5_threshold_0="fellas" VARD_fscore_0.5_threshold_25="fellas" VARD_fscore_0.5_threshold_50="fellas" VARD_fscore_1.0_threshold_0="fellas" VARD_fscore_2.0_threshold_0="fellas" VARD_fscore_2.0_threshold_25="fellas">felles</word>
    <word word_id="SB_J_604.11.28">that</word>
    <word word_id="SB_J_604.11.29">he</word>
    <word word_id="SB_J_604.11.30">thought</word>
    <word word_id="SB_J_604.11.31">I</word>
    <word word_id="SB_J_604.11.32">had</word>
    <word word_id="SB_J_604.11.33" VARD_fscore_0.1_threshold_0="not" VARD_fscore_0.1_threshold_25="not" VARD_fscore_0.1_threshold_50="not" VARD_fscore_0.5_threshold_0="not" VARD_fscore_0.5_threshold_25="not" VARD_fscore_0.5_threshold_50="not" VARD_fscore_0.5_threshold_75="not" VARD_fscore_1.0_threshold_0="not" VARD_fscore_1.0_threshold_25="not" VARD_fscore_1.0_threshold_50="not" VARD_fscore_2.0_threshold_0="not" VARD_fscore_2.0_threshold_25="not" VARD_fscore_2.0_threshold_50="not" VARD_fscore_2.0_threshold_75="not">nott</word>
    <word word_id="SB_J_604.11.34" VARD_fscore_0.1_threshold_0="reckoned" VARD_fscore_0.5_threshold_0="reckoned" VARD_fscore_0.5_threshold_25="reckoned" VARD_fscore_1.0_threshold_0="reckoned" VARD_fscore_2.0_threshold_0="reckoned">reconyd</word>
    <word word_id="SB_J_604.11.35" VARD_fscore_0.1_threshold_0="upon;" VARD_fscore_0.1_threshold_25="upon;" VARD_fscore_0.1_threshold_50="upon;" VARD_fscore_0.5_threshold_0="upon;" VARD_fscore_0.5_threshold_25="upon;" VARD_fscore_0.5_threshold_50="upon;" VARD_fscore_0.5_threshold_75="upon;" VARD_fscore_1.0_threshold_0="upon;" VARD_fscore_1.0_threshold_25="upon;" VARD_fscore_1.0_threshold_50="upon;" VARD_fscore_2.0_threshold_0="upon;" VARD_fscore_2.0_threshold_25="upon;" VARD_fscore_2.0_threshold_50="upon;" VARD_fscore_2.0_threshold_75="upon;">apon;</word>
    <word word_id="SB_J_604.11.36">that</word>
    <word word_id="SB_J_604.11.37">he</word>
    <word word_id="SB_J_604.11.38">being</word>
    <word word_id="SB_J_604.11.39">charged</word>
    <word word_id="SB_J_604.11.40">with</word>
    <word word_id="SB_J_604.11.41" VARD_fscore_0.1_threshold_0="will" VARD_fscore_0.1_threshold_25="will" VARD_fscore_0.1_threshold_50="will" VARD_fscore_0.5_threshold_0="will" VARD_fscore_0.5_threshold_25="will" VARD_fscore_0.5_threshold_50="will" VARD_fscore_1.0_threshold_0="will" VARD_fscore_1.0_threshold_25="will" VARD_fscore_1.0_threshold_50="will" VARD_fscore_2.0_threshold_0="will" VARD_fscore_2.0_threshold_25="will" VARD_fscore_2.0_threshold_50="will">wull</word>
    <word word_id="SB_J_604.11.42" VARD_fscore_0.1_threshold_0="minds" VARD_fscore_0.1_threshold_25="minds" VARD_fscore_0.5_threshold_0="minded" VARD_fscore_0.5_threshold_25="minded" VARD_fscore_0.5_threshold_50="minded" VARD_fscore_1.0_threshold_0="minds" VARD_fscore_1.0_threshold_25="minds" VARD_fscore_2.0_threshold_0="minds" VARD_fscore_2.0_threshold_25="minds">myndith</word>
    <word word_id="SB_J_604.11.43">not</word>
    <word word_id="SB_J_604.11.44">to</word>
    <word word_id="SB_J_604.11.45" VARD_fscore_0.1_threshold_0="meddle" VARD_fscore_0.1_threshold_25="meddle" VARD_fscore_0.1_threshold_50="meddle" VARD_fscore_0.5_threshold_0="meddle" VARD_fscore_0.5_threshold_25="meddle" VARD_fscore_0.5_threshold_50="meddle" VARD_fscore_0.5_threshold_75="meddle" VARD_fscore_1.0_threshold_0="meddle" VARD_fscore_1.0_threshold_25="meddle" VARD_fscore_1.0_threshold_50="meddle" VARD_fscore_2.0_threshold_0="meddle" VARD_fscore_2.0_threshold_25="meddle" VARD_fscore_2.0_threshold_50="meddle" VARD_fscore_2.0_threshold_75="meddle">medle</word>
    <word word_id="SB_J_604.11.46">with</word>
    <word word_id="SB_J_604.11.47" VARD_fscore_0.1_threshold_0="fellas," VARD_fscore_0.5_threshold_0="fellas," VARD_fscore_0.5_threshold_25="fellas," VARD_fscore_0.5_threshold_50="fellas," VARD_fscore_1.0_threshold_0="fellas," VARD_fscore_2.0_threshold_0="fellas," VARD_fscore_2.0_threshold_25="fellas,">felles,</word>
    <word word_id="SB_J_604.11.48">and</word>
    <word word_id="SB_J_604.11.49" VARD_fscore_0.1_threshold_0="therefore" VARD_fscore_0.1_threshold_25="therefore" VARD_fscore_0.1_threshold_50="therefore" VARD_fscore_0.5_threshold_0="therefore" VARD_fscore_0.5_threshold_25="therefore" VARD_fscore_0.5_threshold_50="therefore" VARD_fscore_0.5_threshold_75="therefore" VARD_fscore_1.0_threshold_0="therefore" VARD_fscore_1.0_threshold_25="therefore" VARD_fscore_1.0_threshold_50="therefore" VARD_fscore_2.0_threshold_0="therefore" VARD_fscore_2.0_threshold_25="therefore" VARD_fscore_2.0_threshold_50="therefore" VARD_fscore_2.0_threshold_75="therefore">therfore</word>
    <word word_id="SB_J_604.11.50">wold</word>
    <word word_id="SB_J_604.11.51">have</word>
    <word word_id="SB_J_604.11.52">me</word>
    <word word_id="SB_J_604.11.53">not</word>
    <word word_id="SB_J_604.11.54">to</word>
    <word word_id="SB_J_604.11.55">be</word>
    <word word_id="SB_J_604.11.56" VARD_fscore_0.1_threshold_0="hasty" VARD_fscore_0.1_threshold_25="hasty" VARD_fscore_0.1_threshold_50="hasty" VARD_fscore_0.5_threshold_0="hasty" VARD_fscore_0.5_threshold_25="hasty" VARD_fscore_0.5_threshold_50="hasty" VARD_fscore_0.5_threshold_75="hasty" VARD_fscore_1.0_threshold_0="hasty" VARD_fscore_1.0_threshold_25="hasty" VARD_fscore_1.0_threshold_50="hasty" VARD_fscore_2.0_threshold_0="hasty" VARD_fscore_2.0_threshold_25="hasty" VARD_fscore_2.0_threshold_50="hasty" VARD_fscore_2.0_threshold_75="hasty">hastie</word>
    <word word_id="SB_J_604.11.57">with</word>
    <word word_id="SB_J_604.11.58" VARD_fscore_0.1_threshold_0="nay" VARD_fscore_0.5_threshold_0="nay" VARD_fscore_0.5_threshold_25="nay" VARD_fscore_1.0_threshold_0="nay" VARD_fscore_2.0_threshold_0="nay">ny</word>
    <word word_id="SB_J_604.11.59" VARD_fscore_0.1_threshold_0="customers," VARD_fscore_0.1_threshold_25="customers," VARD_fscore_0.5_threshold_0="customers," VARD_fscore_0.5_threshold_25="customers," VARD_fscore_1.0_threshold_0="customers," VARD_fscore_1.0_threshold_25="customers," VARD_fscore_2.0_threshold_0="customers," VARD_fscore_2.0_threshold_25="customers,">coustomers,</word>
    <word word_id="SB_J_604.11.60">he</word>
    <word word_id="SB_J_604.11.61">not</word>
    <word word_id="SB_J_604.11.62">intending</word>
    <word word_id="SB_J_604.11.63">but</word>
    <word word_id="SB_J_604.11.64">to</word>
    <word word_id="SB_J_604.11.65" VARD_fscore_0.1_threshold_0="meddle" VARD_fscore_0.1_threshold_25="meddle" VARD_fscore_0.1_threshold_50="meddle" VARD_fscore_0.5_threshold_0="meddle" VARD_fscore_0.5_threshold_25="meddle" VARD_fscore_0.5_threshold_50="meddle" VARD_fscore_0.5_threshold_75="meddle" VARD_fscore_1.0_threshold_0="meddle" VARD_fscore_1.0_threshold_25="meddle" VARD_fscore_1.0_threshold_50="meddle" VARD_fscore_2.0_threshold_0="meddle" VARD_fscore_2.0_threshold_25="meddle" VARD_fscore_2.0_threshold_50="meddle" VARD_fscore_2.0_threshold_75="meddle">medle</word>
    <word word_id="SB_J_604.11.66">with</word>
    <word word_id="SB_J_604.11.67">London,</word>
    <word word_id="SB_J_604.11.68">his</word>
    <word word_id="SB_J_604.11.69">old</word>
    <word word_id="SB_J_604.11.70">customers;</word>
    <word word_id="SB_J_604.11.71">to</word>
    <word word_id="SB_J_604.11.72">buy</word>
    <word word_id="SB_J_604.11.73" VARD_fscore_0.1_threshold_0="wainscots" VARD_fscore_0.1_threshold_25="wainscots" VARD_fscore_0.5_threshold_0="wainscots" VARD_fscore_0.5_threshold_25="wainscots" VARD_fscore_1.0_threshold_0="wainscots" VARD_fscore_1.0_threshold_25="wainscots" VARD_fscore_2.0_threshold_0="wainscots" VARD_fscore_2.0_threshold_25="wainscots">wainskottes</word>
    <word word_id="SB_J_604.11.74">for</word>
    <word word_id="SB_J_604.11.75" VARD_fscore_0.1_threshold_0="him," VARD_fscore_0.1_threshold_25="him," VARD_fscore_0.1_threshold_50="him," VARD_fscore_0.5_threshold_0="him," VARD_fscore_0.5_threshold_25="him," VARD_fscore_0.5_threshold_50="him," VARD_fscore_0.5_threshold_75="him," VARD_fscore_1.0_threshold_0="him," VARD_fscore_1.0_threshold_25="him," VARD_fscore_1.0_threshold_50="him," VARD_fscore_2.0_threshold_0="him," VARD_fscore_2.0_threshold_25="him," VARD_fscore_2.0_threshold_50="him," VARD_fscore_2.0_threshold_75="him,">hym,</word>
    <word word_id="SB_J_604.11.76">etc.</word>
    <word word_id="SB_J_604.11.77" VARD_fscore_0.1_threshold_0="Answered" VARD_fscore_0.1_threshold_25="Answered" VARD_fscore_0.1_threshold_50="Answered" VARD_fscore_0.5_threshold_0="Answered" VARD_fscore_0.5_threshold_25="Answered" VARD_fscore_0.5_threshold_50="Answered" VARD_fscore_1.0_threshold_0="Answered" VARD_fscore_1.0_threshold_25="Answered" VARD_fscore_1.0_threshold_50="Answered" VARD_fscore_2.0_threshold_0="Answered" VARD_fscore_2.0_threshold_25="Answered" VARD_fscore_2.0_threshold_50="Answered">Aunswerd</word>
    <word word_id="SB_J_604.11.78">le</word>
    <word word_id="SB_J_604.11.79">20</word>
    <word word_id="SB_J_604.11.80">of</word>
    <word word_id="SB_J_604.11.81">the</word>
    <word word_id="SB_J_604.11.82">same.</word>
    <word word_id="SB_J_604.12.0" VARD_fscore_0.1_threshold_0="SPY" VARD_fscore_0.5_threshold_0="SPY" VARD_fscore_1.0_threshold_0="SPY" VARD_fscore_2.0_threshold_0="SPY">SP</word>
    <word word_id="SB_J_604.12.1">465</word>
    <word word_id="SB_J_604.12.2">f.307</word>
  </letter>
  <VARD>
    <VARD_count VARD_fscore_0.1_threshold_0="141" VARD_fscore_0.5_threshold_0="141" VARD_fscore_1.0_threshold_0="141" VARD_fscore_1.5_threshold_0="141" VARD_fscore_1.9_threshold_0="141" VARD_fscore_2.0_threshold_0="141" VARD_fscore_0.5_threshold_25="131" VARD_fscore_2.0_threshold_25="119" VARD_fscore_0.1_threshold_25="110" VARD_fscore_1.0_threshold_25="110" VARD_fscore_1.5_threshold_25="110" VARD_fscore_1.9_threshold_25="110" VARD_fscore_0.5_threshold_50="109" VARD_fscore_2.0_threshold_50="97" VARD_fscore_0.1_threshold_50="85" VARD_fscore_1.0_threshold_50="85" VARD_fscore_1.5_threshold_50="85" VARD_fscore_1.9_threshold_50="85" VARD_fscore_0.5_threshold_75="49" VARD_fscore_2.0_threshold_75="48"/>
    <VARD_unicity VARD_fscore_1.9_threshold_50="N" VARD_fscore_1.0_threshold_25="Y" VARD_fscore_1.5_threshold_0="N" VARD_fscore_0.1_threshold_25="Y" VARD_fscore_1.5_threshold_25="N" VARD_fscore_2.0_threshold_75="Y" VARD_fscore_1.9_threshold_25="N" VARD_fscore_1.0_threshold_50="Y" VARD_fscore_2.0_threshold_50="Y" VARD_fscore_0.5_threshold_50="Y" VARD_fscore_0.1_threshold_50="Y" VARD_fscore_0.5_threshold_25="Y" VARD_fscore_1.9_threshold_0="N" VARD_fscore_2.0_threshold_25="Y" VARD_fscore_0.5_threshold_0="Y" VARD_fscore_0.5_threshold_75="Y" VARD_fscore_1.0_threshold_0="Y" VARD_fscore_1.5_threshold_50="N" VARD_fscore_0.1_threshold_0="Y" VARD_fscore_2.0_threshold_0="Y"/>
  </VARD>
</root>
